{"source": "google_maps", "identifier": "read design window fashions:southlake, tx", "cached_at": "2025-12-09T08:45:22.791687", "data": {"found": true, "maps_url": "https://www.google.com/maps/search/Read%20Design%20Window%20Fashions%20Southlake%2C%20TX", "name": "Read Design Window Fashions", "rating": 4.8, "review_count": 24, "address": "2757 E Southlake Blvd #100, Southlake, TX 76092", "phone": "(817) 416-7164", "website": null, "status": "closed", "hours": null, "categories": [], "reviews": [{"text": "Reviews are automatically processed to detect inappropriate content like fake reviews and spam. We may take down reviews that are flagged in order to comply with Google policies or legal obligations.", "rating": 5, "date": "", "reviewer_name": "Street View", "source": "google_maps"}, {"text": "\"Received Great service from Jeff and the install was perfectly done!\" \"We purchased window treatments for five rooms from Read Design.\" \"It was a pleasure to work with Read Designs!\"", "rating": 5, "date": "", "reviewer_name": "Anonymous", "source": "google_maps"}], "source": "google_maps"}}