{"source": "google_maps", "identifier": "k&m services, roofing and construction:dallas, tx", "cached_at": "2025-12-09T21:11:13.217475", "data": {"found": true, "maps_url": "https://www.google.com/maps/search/K%26M%20Services%2C%20Roofing%20and%20Construction%20Dallas%2C%20TX", "name": "K&M Services, Roofing and Construction Dallas, TX", "rating": 4.8, "review_count": 21, "address": "11319 Tantor Rd", "phone": "(972) 970-0676", "website": null, "status": "closed", "hours": null, "categories": [], "reviews": [{"text": "K&M Services, Roofing and Construction Roofing contractor \u00b7 11319 Tantor Rd Closed \u00b7 Opens 9\u202fAM Wed \u00b7 (972) 970-0676 K&M Services, Roofing and Construction Roofing contractor \u00b7 4843 Colleyville Blvd Suite #120 Closed \u00b7 Opens 8\u202fAM Wed \u00b7 (817) 918-3940 You've reached the end of the list. Get the most out of Google Maps Map data \u00a92025 GoogleUnited StatesTermsPrivacySend Product Feedback", "rating": 5, "date": "", "reviewer_name": "Anonymous", "source": "google_maps"}], "source": "google_maps"}}