{"source": "google_maps", "identifier": "restoration builders of texas:dallas, tx", "cached_at": "2025-12-09T22:16:30.523308", "data": {"found": true, "maps_url": "https://www.google.com/maps/search/Restoration%20Builders%20of%20Texas%20Dallas%2C%20TX", "name": "Restoration Builders of Texas Dallas, TX", "rating": 4.3, "review_count": 10, "address": "3200 Earhart Drive", "phone": "(888) 588-2144", "website": null, "status": "open", "hours": null, "categories": [], "reviews": [{"text": "Some of these hotel and vacation rental search results may be personalized based on your browsing activity and recent searches on Google, as well as travel confirmations sent to your Gmail. Prices come from Google's partners. All vacation rental reviews and some hotel reviews come from third-party travel sites. Vacation rental reviews are shown as combined ratings of the linked third-party reviews. Reviews aren't verified by Google, but Google checks for and removes fake content when it's identi", "rating": 5, "date": "", "reviewer_name": "Anonymous", "source": "google_maps"}, {"text": "Construction company \u00b7 3200 Earhart Drive Closed \u00b7 Opens 8\u202fAM Wed \u00b7 (888) 588-2144", "rating": 5, "date": "", "reviewer_name": "Renu Inc", "source": "google_maps"}, {"text": "We help reduce the likelihood of mold growth, structural deterioration, & displacement.", "rating": 5, "date": "", "reviewer_name": "Water Mitigation", "source": "google_maps"}, {"text": "Roofing contractor \u00b7 701 E Plano Pkwy Suite 305 Closed \u00b7 Opens 8\u202fAM Wed \u00b7 (214) 823-7663 \"Their workmanship was wonderful and their clean-up was top notch.\"", "rating": 5, "date": "", "reviewer_name": "Restoration Builders", "source": "google_maps"}, {"text": "Roofing contractor \u00b7 777 Central Expy Closed \u00b7 Opens 8\u202fAM Wed \u00b7 (972) 231-4323", "rating": 5, "date": "", "reviewer_name": "Restoration Builders", "source": "google_maps"}, {"text": "General contractor \u00b7 \ue934 \u00b7 11999 Plano Rd # 180 \"They paid attention to every detail, and the end result is beautiful.\" Roofing contractor \u00b7 9330 Lyndon B Johnson Fwy #900 \"The work was completed quickly and to the highest quality standards.\"", "rating": 5, "date": "", "reviewer_name": "Specialty Contractors", "source": "google_maps"}, {"text": "Fire damage restoration service \u00b7 \ue934 \u00b7 4808 Simonton Rd \"R&S did a great job after we had a pipe leak.\"", "rating": 5, "date": "", "reviewer_name": "Restoration Realty", "source": "google_maps"}, {"text": "Roofing contractor \u00b7 8330 Lyndon B Johnson Fwy b656 Closed \u00b7 Opens 8\u202fAM Wed \u00b7 (214) 730-5466 \"Quick response and quality work.\" You've reached the end of the list. Get the most out of Google Maps Map data \u00a92025 GoogleUnited StatesTermsPrivacySend Product Feedback", "rating": 5, "date": "", "reviewer_name": "Trustar Roofing", "source": "google_maps"}], "source": "google_maps"}}