{"source": "google_maps", "identifier": "southwest enclosure systems, inc:fort worth, tx", "cached_at": "2025-12-09T08:32:20.602981", "data": {"found": true, "maps_url": "https://www.google.com/maps/search/Southwest%20Enclosure%20Systems%2C%20Inc%20Fort%20Worth%2C%20TX", "name": "Southwest Enclosure Systems, Inc", "rating": 5.0, "review_count": 1, "address": "1438 Crescent Dr #104, Carrollton, TX 75006", "phone": "(972) 242-8062", "website": null, "status": null, "hours": null, "categories": [], "reviews": [{"text": "Southwest Enclosure Systems, Inc 1438 Crescent Dr #104, Carrollton, TX 75006", "rating": 5, "date": "", "reviewer_name": "Southwest Enclosure", "source": "google_maps"}, {"text": "Reviews are automatically processed to detect inappropriate content like fake reviews and spam. We may take down reviews that are flagged in order to comply with Google policies or legal obligations.", "rating": 5, "date": "", "reviewer_name": "Street View", "source": "google_maps"}, {"text": "Get the most out of Google Maps Map data \u00a92025 GoogleUnited StatesTermsPrivacySend Product Feedback", "rating": 5, "date": "", "reviewer_name": "Texas Shading", "source": "google_maps"}, {"text": "Patio Enclosures Sunrooms\n4.8(647)\nSunroom contractor", "rating": 5, "date": "", "reviewer_name": "Anonymous", "source": "google_maps"}], "source": "google_maps"}}