[
  {
    "contractor_email": "info@riverbendsandler.com",
    "business_name": "Riverbend Sandler Pools",
    "city": "Plano",
    "permit_type": "pool",
    "count": 43,
    "address": "DFW Area"
  },
  {
    "contractor_email": "info@goldmedalpools.com",
    "business_name": "Gold Medal Pools",
    "city": "Plano",
    "permit_type": "pool",
    "count": 43,
    "address": "DFW Area"
  },
  {
    "contractor_email": "info@precisionhomeproducts.com",
    "business_name": "Precision Siding & Construction",
    "city": "Grand Prairie",
    "permit_type": "pool",
    "count": 43,
    "address": "DFW Area"
  }
]