{"source": "contractor_discovery", "identifier": "pool contractor:garland:tx", "cached_at": "2025-12-11T21:20:24.605139", "data": {"category": "pool contractor", "city": "Garland", "state": "TX", "total_found": 60, "contractors": [{"business_name": "Pools123 Dallas-Fort Worth", "city": "Garland", "state": "TX", "address": null, "phone": "(855) 794-6123", "website": null, "google_place_id": "0x864e71739ad5c3c7:0", "google_rating": null, "google_review_count": null, "maps_url": "https://www.google.com/maps/place/Pools123+Dallas-Fort+Worth/data=!4m7!3m6!1s0x864e71739ad5c3c7:0x701d412c8ecb1226!8m2!3d32.7726617!4d-97.3176945!16s%2Fg%2F11rsg8v6z5!19sChIJx8PVmnNxToYRJhLLjixBHXA?authuser=0&hl=en&rclk=1", "categories": ["Pool", "contractor"], "source_category": "pool contractor"}, {"business_name": "Selah Pools", "city": "Garland", "state": "TX", "address": "500 Grapevine Hwy", "phone": "(817) 618-5731", "website": null, "google_place_id": "0x864e792bdcb84647:0", "google_rating": null, "google_review_count": null, "maps_url": "https://www.google.com/maps/place/Selah+Pools/data=!4m7!3m6!1s0x864e792bdcb84647:0x9548b36ce5a1daf2!8m2!3d32.8637358!4d-97.1772483!16s%2Fg%2F11ghft1dcs!19sChIJR0a43Ct5ToYR8tqh5WyzSJU?authuser=0&hl=en&rclk=1", "categories": ["Pool", "contractor"], "source_category": "pool contractor"}, {"business_name": "TXPool", "city": "Garland", "state": "TX", "address": null, "phone": "(888) 794-6839", "website": null, "google_place_id": "0x864c336905afb261:0", "google_rating": null, "google_review_count": null, "maps_url": "https://www.google.com/maps/place/TXPool/data=!4m7!3m6!1s0x864c336905afb261:0xa3cf73e1b576475e!8m2!3d32.772792!4d-97.3177999!16s%2Fg%2F11kvsyrrs3!19sChIJYbKvBWkzTIYRXkd2teFzz6M?authuser=0&hl=en&rclk=1", "categories": ["Pool", "contractor"], "source_category": "pool contractor"}, {"business_name": "DFW Custom Pool", "city": "Garland", "state": "TX", "address": null, "phone": "(972) 943-4831", "website": null, "google_place_id": "0x864e79257ab2f3ef:0", "google_rating": null, "google_review_count": null, "maps_url": "https://www.google.com/maps/place/DFW+Custom+Pool/data=!4m7!3m6!1s0x864e79257ab2f3ef:0x68912730121798a9!8m2!3d32.8386826!4d-97.1827558!16s%2Fg%2F11py6q56m3!19sChIJ7_OyeiV5ToYRqZgXEjAnkWg?authuser=0&hl=en&rclk=1", "categories": ["Pool", "contractor"], "source_category": "pool contractor"}, {"business_name": "Summerhill Pools \u2022 Outdoor Living", "city": "Garland", "state": "TX", "address": "10720 Miller Rd #218", "phone": "(469) 972-5225", "website": null, "google_place_id": "0x864ea0847f113cab:0", "google_rating": null, "google_review_count": null, "maps_url": "https://www.google.com/maps/place/Summerhill+Pools+%E2%80%A2+Outdoor+Living/data=!4m7!3m6!1s0x864ea0847f113cab:0xdd7f43458dcca3b1!8m2!3d32.8939218!4d-96.698733!16s%2Fg%2F1tg7sfdc!19sChIJqzwRf4SgToYRsaPMjUVDf90?authuser=0&hl=en&rclk=1", "categories": ["Pool", "contractor"], "source_category": "pool contractor"}, {"business_name": "Integrity Pools", "city": "Garland", "state": "TX", "address": "1050 N Grove Rd", "phone": "(469) 850-7113", "website": null, "google_place_id": "0x864c1f1078a03559:0", "google_rating": null, "google_review_count": null, "maps_url": "https://www.google.com/maps/place/Integrity+Pools/data=!4m7!3m6!1s0x864c1f1078a03559:0x12fede49abb3895c!8m2!3d32.961458!4d-96.718042!16s%2Fg%2F1tfqg61r!19sChIJWTWgeBAfTIYRXImzq0ne_hI?authuser=0&hl=en&rclk=1", "categories": ["Pool", "contractor"], "source_category": "pool contractor"}, {"business_name": "A & B Gunite", "city": "Garland", "state": "TX", "address": "4316 Garland Dr", "phone": "(817) 498-3690", "website": null, "google_place_id": "0x864e779bc81280ed:0", "google_rating": null, "google_review_count": null, "maps_url": "https://www.google.com/maps/place/A+%26+B+Gunite/data=!4m7!3m6!1s0x864e779bc81280ed:0x7f21d9a7ed2fbf0a!8m2!3d32.8300411!4d-97.2801988!16s%2Fg%2F1thw73zk!19sChIJ7YASyJt3ToYRCr8v7afZIX8?authuser=0&hl=en&rclk=1", "categories": [], "source_category": "pool contractor"}, {"business_name": "Sunstone Pools & Outdoor Living", "city": "Garland", "state": "TX", "address": "1900 Industrial Blvd Ste 200", "phone": "(817) 938-9218", "website": null, "google_place_id": "0x864e75e5e0cc6f9b:0", "google_rating": null, "google_review_count": null, "maps_url": "https://www.google.com/maps/place/Sunstone+Pools+%26+Outdoor+Living/data=!4m7!3m6!1s0x864e75e5e0cc6f9b:0x45548db0ba53916a!8m2!3d32.9023531!4d-97.1380224!16s%2Fg%2F1q64zbmtg!19sChIJm2_M4OV1ToYRapFTurCNVEU?authuser=0&hl=en&rclk=1", "categories": ["Pool", "contractor"], "source_category": "pool contractor"}, {"business_name": "Metroplex Pool", "city": "Garland", "state": "TX", "address": "500 Kimball Ave", "phone": "(855) 955-7665", "website": null, "google_place_id": "0x864dd4b01cf0f6d5:0", "google_rating": null, "google_review_count": null, "maps_url": "https://www.google.com/maps/place/Metroplex+Pool/data=!4m7!3m6!1s0x864dd4b01cf0f6d5:0xb896053caef0ccbf!8m2!3d32.9474817!4d-97.1170485!16s%2Fg%2F11c58n997j!19sChIJ1fbwHLDUTYYRv8zwrjwFlrg?authuser=0&hl=en&rclk=1", "categories": ["Pool", "contractor"], "source_category": "pool contractor"}, {"business_name": "Pool Leak Detection and Repair - Manly Maids", "city": "Garland", "state": "TX", "address": "5736 Shipp Dr", "phone": "(469) 628-6483", "website": null, "google_place_id": "0x864e781b97193f37:0", "google_rating": null, "google_review_count": null, "maps_url": "https://www.google.com/maps/place/Pool+Leak+Detection+and+Repair+-+Manly+Maids/data=!4m7!3m6!1s0x864e781b97193f37:0x93d7f1f701460f19!8m2!3d32.8534895!4d-97.2587414!16s%2Fg%2F1v9lc5hf!19sChIJNz8Zlxt4ToYRGQ9GAffx15M?authuser=0&hl=en&rclk=1", "categories": ["Pool", "contractor"], "source_category": "pool contractor"}, {"business_name": "Dallas Fort Worth Pool Renovations", "city": "Garland", "state": "TX", "address": null, "phone": "(214) 892-3245", "website": null, "google_place_id": "0xa7361d6a6eb5f975:0", "google_rating": null, "google_review_count": null, "maps_url": "https://www.google.com/maps/place/Dallas+Fort+Worth+Pool+Renovations/data=!4m7!3m6!1s0xa7361d6a6eb5f975:0xed287a637c70f21e!8m2!3d32.8380085!4d-97.031894!16s%2Fg%2F11vwpqx0qk!19sChIJdfm1bmodNqcRHvJwfGN6KO0?authuser=0&hl=en&rclk=1", "categories": ["Pool", "contractor"], "source_category": "pool contractor"}, {"business_name": "Innovative PoolTech", "city": "Garland", "state": "TX", "address": "500 Richmond St", "phone": "(469) 279-5553", "website": null, "google_place_id": "0x6fdd4b2672d5c567:0", "google_rating": null, "google_review_count": null, "maps_url": "https://www.google.com/maps/place/Innovative+PoolTech/data=!4m7!3m6!1s0x6fdd4b2672d5c567:0xab1b78c77398c19e!8m2!3d32.8910178!4d-96.6378825!16s%2Fg%2F11sw_17w0t!19sChIJZ8XVciZL3W8RnsGYc8d4G6s?authuser=0&hl=en&rclk=1", "categories": ["Pool", "contractor"], "source_category": "pool contractor"}, {"business_name": "EAV Construction", "city": "Garland", "state": "TX", "address": "221 N 11th St", "phone": "(972) 750-9887", "website": null, "google_place_id": "0x864c1ded5df8ea39:0", "google_rating": null, "google_review_count": null, "maps_url": "https://www.google.com/maps/place/EAV+Construction/data=!4m7!3m6!1s0x864c1ded5df8ea39:0xd6aa28c3eca0151!8m2!3d32.9141966!4d-96.643775!16s%2Fg%2F11g9fk249t!19sChIJOer4Xe0dTIYRUQHKPoyiag0?authuser=0&hl=en&rclk=1", "categories": ["pool", "contractor"], "source_category": "pool contractor"}, {"business_name": "Santorini Pools", "city": "Garland", "state": "TX", "address": "4734 Redwood Dr", "phone": "(469) 554-2741", "website": null, "google_place_id": "0xc52e347f9b41e91:0", "google_rating": null, "google_review_count": null, "maps_url": "https://www.google.com/maps/place/Santorini+Pools/data=!4m7!3m6!1s0xc52e347f9b41e91:0x85eeb976e721746e!8m2!3d32.8556622!4d-96.6128189!16s%2Fg%2F11vd0fwdrm!19sChIJkR60-UfjUgwRbnQh53a57oU?authuser=0&hl=en&rclk=1", "categories": ["Pool"], "source_category": "pool contractor"}, {"business_name": "AquaJon's Pools, LLC", "city": "Garland", "state": "TX", "address": null, "phone": "(817) 240-0885", "website": null, "google_place_id": "0x864e7923c20a26f5:0", "google_rating": null, "google_review_count": null, "maps_url": "https://www.google.com/maps/place/AquaJon%27s+Pools,+LLC/data=!4m7!3m6!1s0x864e7923c20a26f5:0x76185a1ace9a168d!8m2!3d32.8380085!4d-97.1065525!16s%2Fg%2F11h0bcn2hc!19sChIJ9SYKwiN5ToYRjRaazhpaGHY?authuser=0&hl=en&rclk=1", "categories": ["Pool", "contractor"], "source_category": "pool contractor"}, {"business_name": "Weekly Garland Pool Service", "city": "Garland", "state": "TX", "address": null, "phone": "(972) 512-8835", "website": null, "google_place_id": "0x864c1d8dc099141f:0", "google_rating": null, "google_review_count": null, "maps_url": "https://www.google.com/maps/place/Weekly+Garland+Pool+Service/data=!4m7!3m6!1s0x864c1d8dc099141f:0xb6b99ecc8bc84a12!8m2!3d32.917523!4d-96.6352559!16s%2Fg%2F11btww6m2q!19sChIJHxSZwI0dTIYREkrIi8yeubY?authuser=0&hl=en&rclk=1", "categories": ["Pool"], "source_category": "pool contractor"}, {"business_name": "The Blue Lagoons Pools & Spas", "city": "Garland", "state": "TX", "address": null, "phone": "(214) 865-7606", "website": null, "google_place_id": "0x864c1e2c18775ac3:0", "google_rating": null, "google_review_count": null, "maps_url": "https://www.google.com/maps/place/The+Blue+Lagoons+Pools+%26+Spas/data=!4m7!3m6!1s0x864c1e2c18775ac3:0xf569a59633b60c56!8m2!3d32.9099194!4d-96.5337604!16s%2Fg%2F11c59xcx98!19sChIJw1p3GCweTIYRVgy2M5alafU?authuser=0&hl=en&rclk=1", "categories": ["Pool", "contractor"], "source_category": "pool contractor"}, {"business_name": "Sunbelt Pools inc.", "city": "Garland", "state": "TX", "address": "10555 Plano Rd", "phone": "(214) 343-1133", "website": null, "google_place_id": "0x864ea0842484b2f9:0", "google_rating": null, "google_review_count": null, "maps_url": "https://www.google.com/maps/place/Sunbelt+Pools+inc./data=!4m7!3m6!1s0x864ea0842484b2f9:0x16858af4f990945d!8m2!3d32.8924629!4d-96.70079!16s%2Fg%2F1tfv5jvf!19sChIJ-bKEJISgToYRXZSQ-fSKhRY?authuser=0&hl=en&rclk=1", "categories": ["Pool", "contractor"], "source_category": "pool contractor"}, {"business_name": "Big D Pools", "city": "Garland", "state": "TX", "address": "2720 Royal Ln #220", "phone": "(214) 247-7665", "website": null, "google_place_id": "0x864c273520ae7ddf:0", "google_rating": null, "google_review_count": null, "maps_url": "https://www.google.com/maps/place/Big+D+Pools/data=!4m7!3m6!1s0x864c273520ae7ddf:0xd00b900064bfb2d4!8m2!3d32.894607!4d-96.886792!16s%2Fg%2F11ghn_zmxt!19sChIJ332uIDUnTIYR1LK_ZACQC9A?authuser=0&hl=en&rclk=1", "categories": ["Pool", "contractor"], "source_category": "pool contractor"}, {"business_name": "Venture Custom Pools", "city": "Garland", "state": "TX", "address": "4568 State Hwy #121", "phone": "(972) 377-9002", "website": null, "google_place_id": "0x864c3ce1a1c87207:0", "google_rating": null, "google_review_count": null, "maps_url": "https://www.google.com/maps/place/Venture+Custom+Pools/data=!4m7!3m6!1s0x864c3ce1a1c87207:0xb6de2637f4c9fc9c!8m2!3d33.1003637!4d-96.7947456!16s%2Fg%2F1v9lc5bv!19sChIJB3LIoeE8TIYRnPzJ9Dcm3rY?authuser=0&hl=en&rclk=1", "categories": ["Pool", "contractor"], "source_category": "pool contractor"}, {"business_name": "Accent Pools Inc", "city": "Garland", "state": "TX", "address": null, "phone": "(817) 226-7665", "website": null, "google_place_id": "0x864e7d3a1b31fff7:0", "google_rating": 4.4, "google_review_count": 62, "maps_url": "https://www.google.com/maps/place/Accent+Pools+Inc/data=!4m7!3m6!1s0x864e7d3a1b31fff7:0x49a591c59301cf7a!8m2!3d32.7084592!4d-97.1202482!16s%2Fg%2F1tctxz9h!19sChIJ9_8xGzp9ToYRes8Bk8WRpUk?authuser=0&hl=en&rclk=1", "categories": ["Pool", "contractor"], "source_category": "pool contractor"}, {"business_name": "Texas Outdoor Oasis", "city": "Garland", "state": "TX", "address": "2621 Elm Grove Rd", "phone": "(972) 771-1977", "website": null, "google_place_id": "0x864c000adb683a57:0", "google_rating": 4.9, "google_review_count": 297, "maps_url": "https://www.google.com/maps/place/Texas+Outdoor+Oasis/data=!4m7!3m6!1s0x864c000adb683a57:0x5ec46d6a405574a1!8m2!3d32.9674308!4d-96.5427357!16s%2Fg%2F1vyxjtkz!19sChIJVzpo2woATIYRoXRVQGptxF4?authuser=0&hl=en&rclk=1", "categories": ["pool", "contractor"], "source_category": "pool contractor"}, {"business_name": "Liquidus Pool Services", "city": "Garland", "state": "TX", "address": "9959 Royal Ln #6", "phone": "(214) 903-3732", "website": null, "google_place_id": "0x864e9f7089cd6187:0", "google_rating": 4.9, "google_review_count": 401, "maps_url": "https://www.google.com/maps/place/Liquidus+Pool+Services/data=!4m7!3m6!1s0x864e9f7089cd6187:0x35a8d54768e1dd71!8m2!3d32.895082!4d-96.719211!16s%2Fg%2F11g6p7lthh!19sChIJh2HNiXCfToYRcd3haEfVqDU?authuser=0&hl=en&rclk=1", "categories": ["Pool", "contractor"], "source_category": "pool contractor"}, {"business_name": "Petri Pools", "city": "Garland", "state": "TX", "address": "1702 S State Hwy 121 #602", "phone": "(972) 219-8700", "website": null, "google_place_id": "0x864c320d5cb21027:0", "google_rating": 4.8, "google_review_count": 178, "maps_url": "https://www.google.com/maps/place/Petri+Pools/data=!4m7!3m6!1s0x864c320d5cb21027:0x6210b2027f703703!8m2!3d33.0189076!4d-96.9914522!16s%2Fg%2F1w4f8hyb!19sChIJJxCyXA0yTIYRAzdwfwKyEGI?authuser=0&hl=en&rclk=1", "categories": ["Pool", "contractor"], "source_category": "pool contractor"}, {"business_name": "TX Pool & Construction", "city": "Garland", "state": "TX", "address": null, "phone": "(469) 494-9120", "website": null, "google_place_id": "0x864e9ffa4bb5387f:0", "google_rating": 4.8, "google_review_count": 18, "maps_url": "https://www.google.com/maps/place/TX+Pool+%26+Construction/data=!4m7!3m6!1s0x864e9ffa4bb5387f:0xc422886d9a1fd9e1!8m2!3d32.8148682!4d-96.7905769!16s%2Fg%2F11vc9lcf_c!19sChIJfzi1S_qfToYR4dkfmm2IIsQ?authuser=0&hl=en&rclk=1", "categories": ["Pool", "contractor"], "source_category": "pool contractor"}, {"business_name": "FG Pools LLC", "city": "Garland", "state": "TX", "address": "1135 E Plano Pkwy #9", "phone": "(214) 868-3488", "website": null, "google_place_id": "0x864c191fc692fb63:0", "google_rating": 4.9, "google_review_count": 73, "maps_url": "https://www.google.com/maps/place/FG+Pools+LLC/data=!4m7!3m6!1s0x864c191fc692fb63:0xaf24973261384a2a!8m2!3d33.0078942!4d-96.69787!16s%2Fg%2F11t71z_g78!19sChIJY_uSxh8ZTIYRKko4YTKXJK8?authuser=0&hl=en&rclk=1", "categories": ["Pool", "contractor"], "source_category": "pool contractor"}, {"business_name": "Crown Pools", "city": "Garland", "state": "TX", "address": "11204 Garland Rd", "phone": "(214) 328-9137", "website": null, "google_place_id": "0x864ea12264a394b5:0", "google_rating": 4.5, "google_review_count": 101, "maps_url": "https://www.google.com/maps/place/Crown+Pools/data=!4m7!3m6!1s0x864ea12264a394b5:0x74ba1a4f2c34d2d4!8m2!3d32.8475862!4d-96.6844602!16s%2Fg%2F1vyxjt_x!19sChIJtZSjZCKhToYR1NI0LE8aunQ?authuser=0&hl=en&rclk=1", "categories": ["Pool", "contractor"], "source_category": "pool contractor"}, {"business_name": "Custom Pool Plastering", "city": "Garland", "state": "TX", "address": "3230 Keller Hicks Rd", "phone": "(817) 562-2699", "website": null, "google_place_id": "0x864dd99462f93f2f:0", "google_rating": 4.6, "google_review_count": 20, "maps_url": "https://www.google.com/maps/place/Custom+Pool+Plastering/data=!4m7!3m6!1s0x864dd99462f93f2f:0xf303b28ebc515a9!8m2!3d32.9386212!4d-97.2897155!16s%2Fg%2F11g3h_t814!19sChIJLz_5YpTZTYYRqRXF6yg7MA8?authuser=0&hl=en&rclk=1", "categories": ["Pool", "contractor"], "source_category": "pool contractor"}, {"business_name": "Hobert Pools & Spas", "city": "Garland", "state": "TX", "address": null, "phone": "(972) 690-8118", "website": null, "google_place_id": "0x864c1b75a35c18b7:0", "google_rating": 4.2, "google_review_count": 204, "maps_url": "https://www.google.com/maps/place/Hobert+Pools+%26+Spas/data=!4m7!3m6!1s0x864c1b75a35c18b7:0xec9c0f6b0b28855e!8m2!3d33.012054!4d-96.6196028!16s%2Fg%2F1tgdtjwd!19sChIJtxhco3UbTIYRXoUoC2sPnOw?authuser=0&hl=en&rclk=1", "categories": ["Pool", "contractor"], "source_category": "pool contractor"}, {"business_name": "Colin Irons Diving & Pool Service, Inc.", "city": "Garland", "state": "TX", "address": null, "phone": "(940) 484-4468", "website": null, "google_place_id": "0x864c4cb4019f7947:0", "google_rating": 4.6, "google_review_count": 173, "maps_url": "https://www.google.com/maps/place/Colin+Irons+Diving+%26+Pool+Service,+Inc./data=!4m7!3m6!1s0x864c4cb4019f7947:0x1ce4ad1beea332e8!8m2!3d32.9543685!4d-96.9980619!16s%2Fg%2F11c535jy86!19sChIJR3mfAbRMTIYR6DKj7hut5Bw?authuser=0&hl=en&rclk=1", "categories": ["Pool", "contractor"], "source_category": "pool contractor"}, {"business_name": "Living Water Custom Pools", "city": "Garland", "state": "TX", "address": "801 K Ave suite #11", "phone": "(469) 662-3600", "website": null, "google_place_id": "0x864c18e298988d7b:0", "google_rating": 4.8, "google_review_count": 46, "maps_url": "https://www.google.com/maps/place/Living+Water+Custom+Pools/data=!4m7!3m6!1s0x864c18e298988d7b:0xf5366192d458604c!8m2!3d33.0099059!4d-96.6997245!16s%2Fg%2F11c6cxbrmf!19sChIJe42YmOIYTIYRTGBY1JJhNvU?authuser=0&hl=en&rclk=1", "categories": ["Pool", "contractor"], "source_category": "pool contractor"}, {"business_name": "Signature Pool and Patio", "city": "Garland", "state": "TX", "address": "3905 Melcer Dr #504", "phone": "(214) 501-4835", "website": null, "google_place_id": "0x864ea93f609fc09f:0", "google_rating": 4.6, "google_review_count": 17, "maps_url": "https://www.google.com/maps/place/Signature+Pool+and+Patio/data=!4m7!3m6!1s0x864ea93f609fc09f:0x24a7642859d3edd3!8m2!3d32.9053676!4d-96.5652539!16s%2Fg%2F11r_xcmkhc!19sChIJn8CfYD-pToYR0-3TWShkpyQ?authuser=0&hl=en&rclk=1", "categories": ["Pool", "contractor"], "source_category": "pool contractor"}, {"business_name": "Paradise Pools Of Texas", "city": "Garland", "state": "TX", "address": null, "phone": "(469) 887-1867", "website": null, "google_place_id": "0x401d06d1cd6bcc79:0", "google_rating": 5.0, "google_review_count": 4, "maps_url": "https://www.google.com/maps/place/Paradise+Pools+Of+Texas/data=!4m7!3m6!1s0x401d06d1cd6bcc79:0x1df0bb4350c259e5!8m2!3d32.9406389!4d-96.7431263!16s%2Fg%2F11vm1g9fx2!19sChIJecxrzdEGHUAR5VnCUEO78B0?authuser=0&hl=en&rclk=1", "categories": ["Pool", "contractor"], "source_category": "pool contractor"}, {"business_name": "HydroCare Pools LLC", "city": "Garland", "state": "TX", "address": null, "phone": "(214) 621-2408", "website": null, "google_place_id": "0x6294b2581edc266b:0", "google_rating": 5.0, "google_review_count": 37, "maps_url": "https://www.google.com/maps/place/HydroCare+Pools+LLC/data=!4m7!3m6!1s0x6294b2581edc266b:0xcde9c5932ace6818!8m2!3d32.916304!4d-96.711846!16s%2Fg%2F11t17vk8k9!19sChIJaybcHliylGIRGGjOKpPF6c0?authuser=0&hl=en&rclk=1", "categories": ["Pool", "contractor"], "source_category": "pool contractor"}, {"business_name": "All About Pools", "city": "Garland", "state": "TX", "address": null, "phone": "(972) 475-7665", "website": null, "google_place_id": "0x864c0273ea4930cd:0", "google_rating": 4.6, "google_review_count": 142, "maps_url": "https://www.google.com/maps/place/All+About+Pools/data=!4m7!3m6!1s0x864c0273ea4930cd:0xe3b34e2230057663!8m2!3d32.916044!4d-96.51854!16s%2Fg%2F1tp8_fms!19sChIJzTBJ6nMCTIYRY3YFMCJOs-M?authuser=0&hl=en&rclk=1", "categories": ["Pool"], "source_category": "pool contractor"}, {"business_name": "Poseidon Pools Service and Repair", "city": "Garland", "state": "TX", "address": null, "phone": "(682) 704-3833", "website": null, "google_place_id": "0x864e7f9e2f0f0c0f:0", "google_rating": 4.4, "google_review_count": 7, "maps_url": "https://www.google.com/maps/place/Poseidon+Pools+Service+and+Repair/data=!4m7!3m6!1s0x864e7f9e2f0f0c0f:0x251a9a4b296bc2ce!8m2!3d32.862017!4d-96.9532885!16s%2Fg%2F11hdy4cmxq!19sChIJDwwPL55_ToYRzsJrKUuaGiU?authuser=0&hl=en&rclk=1", "categories": ["Pool", "contractor"], "source_category": "pool contractor"}, {"business_name": "Sterling Pool Service, Inc.", "city": "Garland", "state": "TX", "address": "5250 S State Hwy 78 #750", "phone": "(888) 973-0274", "website": null, "google_place_id": "0x864c02e068f9017b:0", "google_rating": 4.7, "google_review_count": 27, "maps_url": "https://www.google.com/maps/place/Sterling+Pool+Service,+Inc./data=!4m7!3m6!1s0x864c02e068f9017b:0xf63a5e93f6309e04!8m2!3d32.969939!4d-96.6029662!16s%2Fg%2F12627y3s4!19sChIJewH5aOACTIYRBJ4w9pNeOvY?authuser=0&hl=en&rclk=1", "categories": ["Pool"], "source_category": "pool contractor"}, {"business_name": "El Dorado Pools + Outdoors", "city": "Garland", "state": "TX", "address": "4514 Rowlett Rd", "phone": "(214) 607-4700", "website": null, "google_place_id": "0x864ea803667433c3:0", "google_rating": 3.5, "google_review_count": 22, "maps_url": "https://www.google.com/maps/place/El+Dorado+Pools+%2B+Outdoors/data=!4m7!3m6!1s0x864ea803667433c3:0xc6b9a8db8ea21315!8m2!3d32.901499!4d-96.569089!16s%2Fg%2F1vs5x3wb!19sChIJwzN0ZgOoToYRFROijtuoucY?authuser=0&hl=en&rclk=1", "categories": ["Pool", "contractor"], "source_category": "pool contractor"}, {"business_name": "FK POOL SERVICE LLC", "city": "Garland", "state": "TX", "address": "2518 Meadow Ln", "phone": "(469) 231-7959", "website": null, "google_place_id": "0x864c1d653d99ee7f:0", "google_rating": 5.0, "google_review_count": 4, "maps_url": "https://www.google.com/maps/place/FK+POOL+SERVICE+LLC/data=!4m7!3m6!1s0x864c1d653d99ee7f:0xd4f7d6f69750a108!8m2!3d32.9378913!4d-96.6209687!16s%2Fg%2F11w584dr3h!19sChIJf-6ZPWUdTIYRCKFQl_bW99Q?authuser=0&hl=en&rclk=1", "categories": ["POOL"], "source_category": "pool contractor"}, {"business_name": "Morton Pool Solutions / Renovations", "city": "Garland", "state": "TX", "address": null, "phone": "(469) 571-9608", "website": null, "google_place_id": "0x864c059586574faf:0", "google_rating": 5.0, "google_review_count": 93, "maps_url": "https://www.google.com/maps/place/Morton+Pool+Solutions+%2F+Renovations/data=!4m7!3m6!1s0x864c059586574faf:0xa44229770b7e8994!8m2!3d33.0195466!4d-96.5409175!16s%2Fg%2F11ghtnwx6f!19sChIJr09XhpUFTIYRlIl-C3cpQqQ?authuser=0&hl=en&rclk=1", "categories": ["Pool", "contractor"], "source_category": "pool contractor"}, {"business_name": "Lucent Pools", "city": "Garland", "state": "TX", "address": null, "phone": "(817) 339-6770", "website": null, "google_place_id": "0x864dd924306f86ff:0", "google_rating": 5.0, "google_review_count": 10, "maps_url": "https://www.google.com/maps/place/Lucent+Pools/data=!4m7!3m6!1s0x864dd924306f86ff:0x3354164222c73573!8m2!3d32.946489!4d-96.916152!16s%2Fg%2F11btl_vg6s!19sChIJ_4ZvMCTZTYYRczXHIkIWVDM?authuser=0&hl=en&rclk=1", "categories": ["Pool", "contractor"], "source_category": "pool contractor"}, {"business_name": "Aqua Clean Pool Service", "city": "Garland", "state": "TX", "address": "7020 Sanders Ln", "phone": "(972) 527-2782", "website": null, "google_place_id": "0x864c19cdf3851e1b:0", "google_rating": 4.6, "google_review_count": 84, "maps_url": "https://www.google.com/maps/place/Aqua+Clean+Pool+Service/data=!4m7!3m6!1s0x864c19cdf3851e1b:0x6e103ffb4fb2839b!8m2!3d33.0728779!4d-96.7178549!16s%2Fg%2F1tpll3vz!19sChIJGx6F880ZTIYRm4OyT_s_EG4?authuser=0&hl=en&rclk=1", "categories": ["Pool", "contractor"], "source_category": "pool contractor"}, {"business_name": "Pool Chlor", "city": "Garland", "state": "TX", "address": "2222 Executive Dr", "phone": "(972) 271-7079", "website": null, "google_place_id": "0x864ea0a34642c1ad:0", "google_rating": 4.4, "google_review_count": 65, "maps_url": "https://www.google.com/maps/place/Pool+Chlor/data=!4m7!3m6!1s0x864ea0a34642c1ad:0xaa4eef8234ec7b60!8m2!3d32.8902923!4d-96.6810782!16s%2Fg%2F1tjz8c31!19sChIJrcFCRqOgToYRYHvsNILvTqo?authuser=0&hl=en&rclk=1", "categories": ["Pool"], "source_category": "pool contractor"}, {"business_name": "Creative Pools", "city": "Garland", "state": "TX", "address": "7525 Holly Hill Dr", "phone": "(214) 373-7665", "website": null, "google_place_id": "0x864e9ff400000001:0", "google_rating": 4.7, "google_review_count": 12, "maps_url": "https://www.google.com/maps/place/Creative+Pools/data=!4m7!3m6!1s0x864e9ff400000001:0x5ec414c128cfd53f!8m2!3d32.8798071!4d-96.7547522!16s%2Fg%2F1tvq4jwg!19sChIJAQAAAPSfToYRP9XPKMEUxF4?authuser=0&hl=en&rclk=1", "categories": ["Pool", "contractor"], "source_category": "pool contractor"}, {"business_name": "J & M Pool Plastering", "city": "Garland", "state": "TX", "address": "2765 W Kingsley Rd", "phone": "(972) 278-4498", "website": null, "google_place_id": "0x864c1d99d4ab78cb:0", "google_rating": 3.5, "google_review_count": 28, "maps_url": "https://www.google.com/maps/place/J+%26+M+Pool+Plastering/data=!4m7!3m6!1s0x864c1d99d4ab78cb:0x2fb8ec4574382ca3!8m2!3d32.8792076!4d-96.6698618!16s%2Fg%2F1tj96trp!19sChIJy3ir1JkdTIYRoyw4dEXsuC8?authuser=0&hl=en&rclk=1", "categories": ["Pool", "contractor"], "source_category": "pool contractor"}, {"business_name": "Texas Fiberglass Pools Inc.", "city": "Garland", "state": "TX", "address": "5301 Alpha Rd Suite 205", "phone": "(972) 241-6608", "website": null, "google_place_id": "0x864c27edc27d85e9:0", "google_rating": 4.6, "google_review_count": 88, "maps_url": "https://www.google.com/maps/place/Texas+Fiberglass+Pools+Inc./data=!4m7!3m6!1s0x864c27edc27d85e9:0x63e9ff2e110b6e3c!8m2!3d32.9341807!4d-96.8170538!16s%2Fg%2F12mm854j7!19sChIJ6YV9wu0nTIYRPG4LES7_6WM?authuser=0&hl=en&rclk=1", "categories": ["Pool", "contractor"], "source_category": "pool contractor"}, {"business_name": "Aqua Architects", "city": "Garland", "state": "TX", "address": null, "phone": "(469) 571-0195", "website": null, "google_place_id": "0xae5e22ca6f3a9201:0", "google_rating": 5.0, "google_review_count": 21, "maps_url": "https://www.google.com/maps/place/Aqua+Architects/data=!4m7!3m6!1s0xae5e22ca6f3a9201:0x5391d42bac8c3ce5!8m2!3d32.7985011!4d-96.5672613!16s%2Fg%2F11vzlzj144!19sChIJAZI6b8oiXq4R5TyMrCvUkVM?authuser=0&hl=en&rclk=1", "categories": ["pool", "contractor"], "source_category": "pool contractor"}, {"business_name": "TX AquaDoc Pool Leak Detection & Repair", "city": "Garland", "state": "TX", "address": null, "phone": "(817) 727-7579", "website": null, "google_place_id": "0x6ac40514b4df9369:0", "google_rating": 4.9, "google_review_count": 106, "maps_url": "https://www.google.com/maps/place/TX+AquaDoc+Pool+Leak+Detection+%26+Repair/data=!4m7!3m6!1s0x6ac40514b4df9369:0x872416a50edf3b98!8m2!3d32.1365614!4d-97.147446!16s%2Fg%2F11trxgx_nk!19sChIJaZPftBQFxGoRmDvfDqUWJIc?authuser=0&hl=en&rclk=1", "categories": ["Pool", "contractor"], "source_category": "pool contractor"}, {"business_name": "Pool Xperts", "city": "Garland", "state": "TX", "address": null, "phone": "(469) 215-7946", "website": null, "google_place_id": "0x864ead46b9dda83f:0", "google_rating": 4.9, "google_review_count": 55, "maps_url": "https://www.google.com/maps/place/Pool+Xperts/data=!4m7!3m6!1s0x864ead46b9dda83f:0x88049d457a56151b!8m2!3d32.8464887!4d-96.3804347!16s%2Fg%2F11c20qk7zj!19sChIJP6jduUatToYRGxVWekWdBIg?authuser=0&hl=en&rclk=1", "categories": ["Pool", "contractor"], "source_category": "pool contractor"}, {"business_name": "Las Colinas Pools & Spas", "city": "Garland", "state": "TX", "address": "1200 Jupiter Rd", "phone": "(972) 979-3885", "website": null, "google_place_id": "0x864c1f737d497a67:0", "google_rating": 5.0, "google_review_count": 5, "maps_url": "https://www.google.com/maps/place/Las+Colinas+Pools+%26+Spas/data=!4m7!3m6!1s0x864c1f737d497a67:0xe3a7e02935330bf3!8m2!3d33.015835!4d-96.6809524!16s%2Fg%2F1td2zw3j!19sChIJZ3pJfXMfTIYR8wszNSngp-M?authuser=0&hl=en&rclk=1", "categories": ["Pool", "contractor"], "source_category": "pool contractor"}, {"business_name": "Palm Springs Pool Service", "city": "Garland", "state": "TX", "address": "3525 Security St", "phone": "(214) 358-3268", "website": null, "google_place_id": "0x864ea0a032c91ae5:0", "google_rating": 3.9, "google_review_count": 7, "maps_url": "https://www.google.com/maps/place/Palm+Springs+Pool+Service/data=!4m7!3m6!1s0x864ea0a032c91ae5:0xf736df712d528b9d!8m2!3d32.8976445!4d-96.6844327!16s%2Fg%2F11bxfmxxfp!19sChIJ5RrJMqCgToYRnYtSLXHfNvc?authuser=0&hl=en&rclk=1", "categories": ["Pool"], "source_category": "pool contractor"}, {"business_name": "First Class Pools & Spas Dallas", "city": "Garland", "state": "TX", "address": "4411 Glenview Dr", "phone": "(972) 437-0844", "website": null, "google_place_id": "0x864c1d7029d04b39:0", "google_rating": 4.3, "google_review_count": 6, "maps_url": "https://www.google.com/maps/place/First+Class+Pools+%26+Spas+Dallas/data=!4m7!3m6!1s0x864c1d7029d04b39:0xefa0ae67ec618002!8m2!3d32.9947853!4d-96.5818055!16s%2Fg%2F11j969nsxr!19sChIJOUvQKXAdTIYRAoBh7GeuoO8?authuser=0&hl=en&rclk=1", "categories": ["Pool", "contractor"], "source_category": "pool contractor"}, {"business_name": "Lone Star Fiberglass Pools DFW LLC", "city": "Garland", "state": "TX", "address": null, "phone": "(214) 454-6071", "website": null, "google_place_id": "0x864c1fbf3556f153:0", "google_rating": 3.7, "google_review_count": 17, "maps_url": "https://www.google.com/maps/place/Lone+Star+Fiberglass+Pools+DFW+LLC/data=!4m7!3m6!1s0x864c1fbf3556f153:0xf9903a697efe5e26!8m2!3d32.7932488!4d-96.6170129!16s%2Fg%2F11h07gxhh5!19sChIJU_FWNb8fTIYRJl7-fmk6kPk?authuser=0&hl=en&rclk=1", "categories": ["Pool", "contractor"], "source_category": "pool contractor"}, {"business_name": "Elite Swimming Pool & Spa Service", "city": "Garland", "state": "TX", "address": "3021 Ridge Rd a250", "phone": "(469) 855-4505", "website": null, "google_place_id": "0x864eaa3f957db4ab:0", "google_rating": 4.8, "google_review_count": 125, "maps_url": "https://www.google.com/maps/place/Elite+Swimming+Pool+%26+Spa+Service/data=!4m7!3m6!1s0x864eaa3f957db4ab:0x8e55866dc09fd67e!8m2!3d32.887541!4d-96.47298!16s%2Fg%2F11cncrx26x!19sChIJq7R9lT-qToYRftafwG2GVY4?authuser=0&hl=en&rclk=1", "categories": ["Pool", "contractor"], "source_category": "pool contractor"}, {"business_name": "Aquatic Arts Pool N Spa", "city": "Garland", "state": "TX", "address": null, "phone": "(469) 960-3740", "website": null, "google_place_id": "0x80dbf8d0fc161c65:0", "google_rating": 4.8, "google_review_count": 200, "maps_url": "https://www.google.com/maps/place/Aquatic+Arts+Pool+N+Spa/data=!4m7!3m6!1s0x80dbf8d0fc161c65:0xc0bc7483d5465c9!8m2!3d32.9261219!4d-96.4597925!16s%2Fg%2F1tgk0y8w!19sChIJZRwW_ND424ARyWVUPUjHCww?authuser=0&hl=en&rclk=1", "categories": ["Pool", "contractor"], "source_category": "pool contractor"}, {"business_name": "Pura Vida Pools", "city": "Garland", "state": "TX", "address": "1222 Meandering Way", "phone": null, "website": null, "google_place_id": "0x864c1d0ec09ddf73:0", "google_rating": null, "google_review_count": null, "maps_url": "https://www.google.com/maps/place/Pura+Vida+Pools/data=!4m7!3m6!1s0x864c1d0ec09ddf73:0xa54a3ac3c1002425!8m2!3d32.9336129!4d-96.6145433!16s%2Fg%2F11fll659gc!19sChIJc9-dwA4dTIYRJSQAwcM6SqU?authuser=0&hl=en&rclk=1", "categories": ["Pool", "contractor"], "source_category": "pool contractor"}, {"business_name": "Custom Design Pools", "city": "Garland", "state": "TX", "address": "3707 Meadow Wood Ct", "phone": "(972) 880-1209", "website": null, "google_place_id": "0x864c18ecf7dad425:0", "google_rating": 4.0, "google_review_count": 4, "maps_url": "https://www.google.com/maps/place/Custom+Design+Pools/data=!4m7!3m6!1s0x864c18ecf7dad425:0xc4ee7267d8185491!8m2!3d32.9917566!4d-96.5875624!16s%2Fg%2F1hc1vt6fh!19sChIJJdTa9-wYTIYRkVQY2Gdy7sQ?authuser=0&hl=en&rclk=1", "categories": ["Pool", "contractor"], "source_category": "pool contractor"}, {"business_name": "Richardson Blue Pools & Spas", "city": "Garland", "state": "TX", "address": null, "phone": "(214) 919-5868", "website": null, "google_place_id": "0x864c1ed8b77a0b8b:0", "google_rating": 4.9, "google_review_count": 83, "maps_url": "https://www.google.com/maps/place/Richardson+Blue+Pools+%26+Spas/data=!4m7!3m6!1s0x864c1ed8b77a0b8b:0x13b6e9e5a3d4fe4!8m2!3d32.9777251!4d-96.695035!16s%2Fg%2F11c1vkdzcz!19sChIJiwt6t9geTIYR5E89Wp5uOwE?authuser=0&hl=en&rclk=1", "categories": ["Pool", "contractor"], "source_category": "pool contractor"}, {"business_name": "Canyon Oak Pools", "city": "Garland", "state": "TX", "address": null, "phone": "(972) 561-9090", "website": null, "google_place_id": "0x864c13af94061c17:0", "google_rating": 5.0, "google_review_count": 88, "maps_url": "https://www.google.com/maps/place/Canyon+Oak+Pools/data=!4m7!3m6!1s0x864c13af94061c17:0xbb8ad5bc53180220!8m2!3d33.1430874!4d-96.7165297!16s%2Fg%2F11q9rf5bn5!19sChIJFxwGlK8TTIYRIAIYU7zVirs?authuser=0&hl=en&rclk=1", "categories": ["Pool", "contractor"], "source_category": "pool contractor"}, {"business_name": "Johnston Custom Pools", "city": "Garland", "state": "TX", "address": null, "phone": "(817) 475-9785", "website": null, "google_place_id": "0x864dd6462883a4dd:0", "google_rating": 5.0, "google_review_count": 7, "maps_url": "https://www.google.com/maps/place/Johnston+Custom+Pools/data=!4m7!3m6!1s0x864dd6462883a4dd:0xcca9bb3a67da5e30!8m2!3d32.783911!4d-97.291853!16s%2Fg%2F11c58nhr6j!19sChIJ3aSDKEbWTYYRMF7aZzq7qcw?authuser=0&hl=en&rclk=1", "categories": ["Pool", "contractor"], "source_category": "pool contractor"}]}}