{"source": "contractor_discovery", "identifier": "hvac contractor:dallas:tx", "cached_at": "2025-12-11T08:56:10.184417", "data": {"category": "HVAC contractor", "city": "Dallas", "state": "TX", "total_found": 40, "contractors": [{"business_name": "Dallas Heating and Air Conditioning", "city": "Dallas", "state": "TX", "address": "5050 Quorum Dr Ste 700", "phone": "(214) 831-8061", "website": null, "google_place_id": "0x864c21ef5655b577:0", "google_rating": null, "google_review_count": null, "maps_url": "https://www.google.com/maps/place/Dallas+Heating+and+Air+Conditioning/data=!4m7!3m6!1s0x864c21ef5655b577:0x63a4a927593817cf!8m2!3d32.9483505!4d-96.82413!16s%2Fg%2F11lgsmlmw1!19sChIJd7VVVu8hTIYRzxc4WSeppGM?authuser=0&hl=en&rclk=1", "categories": ["Heating", "contractor"], "source_category": "HVAC contractor"}, {"business_name": "Unlimited Air Conditioning and Heating", "city": "Dallas", "state": "TX", "address": "822 Woodlawn Ave", "phone": "(945) 998-7066", "website": null, "google_place_id": "0x864e99815977c3f3:0", "google_rating": null, "google_review_count": null, "maps_url": "https://www.google.com/maps/place/Unlimited+Air+Conditioning+and+Heating/data=!4m7!3m6!1s0x864e99815977c3f3:0x6deb1de8615c71ac!8m2!3d32.7530763!4d-96.8300605!16s%2Fg%2F1tmbwjhr!19sChIJ88N3WYGZToYRrHFcYegd620?authuser=0&hl=en&rclk=1", "categories": ["Air Conditioning", "contractor"], "source_category": "HVAC contractor"}, {"business_name": "Lex - Air Conditioning, Heating, Plumbing, Electrical", "city": "Dallas", "state": "TX", "address": null, "phone": "(972) 424-2473", "website": null, "google_place_id": "0x864c18476f7b6525:0", "google_rating": null, "google_review_count": null, "maps_url": "https://www.google.com/maps/place/Lex+-+Air+Conditioning,+Heating,+Plumbing,+Electrical/data=!4m7!3m6!1s0x864c18476f7b6525:0x7a08652d84b03ed0!8m2!3d32.985682!4d-96.805333!16s%2Fg%2F1tdsk5f9!19sChIJJWV7b0cYTIYR0D6whC1lCHo?authuser=0&hl=en&rclk=1", "categories": ["Plumbing", "Electrical", "Air Conditioning", "contractor"], "source_category": "HVAC contractor"}, {"business_name": "Texas AirZone LLC", "city": "Dallas", "state": "TX", "address": "10763 Mapleridge Dr", "phone": "(214) 851-3886", "website": null, "google_place_id": "0x864ea080fba6f511:0", "google_rating": null, "google_review_count": null, "maps_url": "https://www.google.com/maps/place/Texas+AirZone+LLC/data=!4m7!3m6!1s0x864ea080fba6f511:0xceec20ac5cbf7fd4!8m2!3d32.8806583!4d-96.6964393!16s%2Fg%2F1tgzbrww!19sChIJEfWm-4CgToYR1H-_XKwg7M4?authuser=0&hl=en&rclk=1", "categories": ["HVAC", "contractor"], "source_category": "HVAC contractor"}, {"business_name": "Quigley Heating & Air Conditioning of Dallas", "city": "Dallas", "state": "TX", "address": "13720 Diplomat Dr", "phone": "(214) 526-8533", "website": null, "google_place_id": "0x864e9c2190121f47:0", "google_rating": null, "google_review_count": null, "maps_url": "https://www.google.com/maps/place/Quigley+Heating+%26+Air+Conditioning+of+Dallas/data=!4m7!3m6!1s0x864e9c2190121f47:0xc544ff82ece50980!8m2!3d32.9287087!4d-96.9065335!16s%2Fg%2F1tdn92bt!19sChIJRx8SkCGcToYRgAnl7IL_RMU?authuser=0&hl=en&rclk=1", "categories": ["Heating", "contractor"], "source_category": "HVAC contractor"}, {"business_name": "Metro Air Conditioning Heating & Services", "city": "Dallas", "state": "TX", "address": "126 W Illinois Ave", "phone": "(214) 304-7658", "website": null, "google_place_id": "0x864e99e35d32d35b:0", "google_rating": null, "google_review_count": null, "maps_url": "https://www.google.com/maps/place/Metro+Air+Conditioning+Heating+%26+Services/data=!4m7!3m6!1s0x864e99e35d32d35b:0xbcd618064b160cf2!8m2!3d32.7201503!4d-96.8240343!16s%2Fg%2F1tf2y66m!19sChIJW9MyXeOZToYR8gwWSwYY1rw?authuser=0&hl=en&rclk=1", "categories": ["Air Conditioning", "contractor"], "source_category": "HVAC contractor"}, {"business_name": "Cody & Sons Plumbing, Heating & Air", "city": "Dallas", "state": "TX", "address": "209 W Clarendon Dr", "phone": "(214) 894-9629", "website": null, "google_place_id": "0x864e99f2bbb36c73:0", "google_rating": null, "google_review_count": null, "maps_url": "https://www.google.com/maps/place/Cody+%26+Sons+Plumbing,+Heating+%26+Air/data=!4m7!3m6!1s0x864e99f2bbb36c73:0xd04d24519abf8811!8m2!3d32.7347117!4d-96.8252793!16s%2Fg%2F1tmy5gcj!19sChIJc2yzu_KZToYREYi_mlEkTdA?authuser=0&hl=en&rclk=1", "categories": ["Plumbing", "Heating", "contractor"], "source_category": "HVAC contractor"}, {"business_name": "Harlen Johnson Heating, Air & Plumbing", "city": "Dallas", "state": "TX", "address": "2643 Royal Ln", "phone": "(972) 975-5051", "website": null, "google_place_id": "0x864c278f573bfbfb:0", "google_rating": null, "google_review_count": null, "maps_url": "https://www.google.com/maps/place/Harlen+Johnson+Heating,+Air+%26+Plumbing/data=!4m7!3m6!1s0x864c278f573bfbfb:0x381d6595596efbc6!8m2!3d32.8955751!4d-96.8890027!16s%2Fg%2F1tfc6__0!19sChIJ-_s7V48nTIYRxvtuWZVlHTg?authuser=0&hl=en&rclk=1", "categories": ["Plumbing", "Heating", "contractor"], "source_category": "HVAC contractor"}, {"business_name": "One Hour Air Conditioning & Heating of Dallas", "city": "Dallas", "state": "TX", "address": "1608 Whitlock Ln Unit J", "phone": "(682) 327-0948", "website": null, "google_place_id": "0x864c27a24ad8cc25:0", "google_rating": null, "google_review_count": null, "maps_url": "https://www.google.com/maps/place/One+Hour+Air+Conditioning+%26+Heating+of+Dallas/data=!4m7!3m6!1s0x864c27a24ad8cc25:0x618510e3e00de6c0!8m2!3d32.9688094!4d-96.9176221!16s%2Fg%2F11pwb636yr!19sChIJJczYSqInTIYRwOYN4OMQhWE?authuser=0&hl=en&rclk=1", "categories": ["Air Conditioning", "contractor"], "source_category": "HVAC contractor"}, {"business_name": "Coolinary Arts Heating & Cooling", "city": "Dallas", "state": "TX", "address": "5200 McKinney Ave", "phone": "(972) 975-2665", "website": null, "google_place_id": "0x864eb0dc368439bf:0", "google_rating": null, "google_review_count": null, "maps_url": "https://www.google.com/maps/place/Coolinary+Arts+Heating+%26+Cooling/data=!4m7!3m6!1s0x864eb0dc368439bf:0x8bc27d41c0be5254!8m2!3d32.8296948!4d-96.7831111!16s%2Fg%2F1tdl1zsc!19sChIJvzmENtywToYRVFK-wEF9wos?authuser=0&hl=en&rclk=1", "categories": ["Heating", "contractor"], "source_category": "HVAC contractor"}, {"business_name": "M. B. Kiser Heating & Air Conditioning Co. Inc.", "city": "Dallas", "state": "TX", "address": "10549 Denton Dr in", "phone": "(214) 823-9958", "website": null, "google_place_id": "0x864e9d8c146db2c5:0", "google_rating": null, "google_review_count": null, "maps_url": "https://www.google.com/maps/place/M.+B.+Kiser+Heating+%26+Air+Conditioning+Co.+Inc./data=!4m7!3m6!1s0x864e9d8c146db2c5:0xd6458a4f75155123!8m2!3d32.8681613!4d-96.8806035!16s%2Fg%2F11jfgnbzsk!19sChIJxbJtFIydToYRI1EVdU-KRdY?authuser=0&hl=en&rclk=1", "categories": ["Heating", "contractor"], "source_category": "HVAC contractor"}, {"business_name": "Alpha Heating & Cooling Llc. HVAC Dallas", "city": "Dallas", "state": "TX", "address": "1910 Pacific Ave Suite #12000 Floor 12", "phone": "(214) 945-8799", "website": null, "google_place_id": "0x864e99ccbfccc41b:0", "google_rating": null, "google_review_count": null, "maps_url": "https://www.google.com/maps/place/Alpha+Heating+%26+Cooling+Llc.+HVAC+Dallas/data=!4m7!3m6!1s0x864e99ccbfccc41b:0x8bbdeb5d1dbb17d3!8m2!3d32.7826453!4d-96.7954613!16s%2Fg%2F11q96d1050!19sChIJG8TMv8yZToYR0xe7HV3rvYs?authuser=0&hl=en&rclk=1", "categories": ["Heating", "contractor"], "source_category": "HVAC contractor"}, {"business_name": "Malcolm's Heating & Air", "city": "Dallas", "state": "TX", "address": "3416 Wendell Dr", "phone": "(817) 333-7310", "website": null, "google_place_id": "0x864e79c54cd6a013:0", "google_rating": null, "google_review_count": null, "maps_url": "https://www.google.com/maps/place/Malcolm%27s+Heating+%26+Air/data=!4m7!3m6!1s0x864e79c54cd6a013:0x679dc00f473abedf!8m2!3d32.8116735!4d-97.2544423!16s%2Fg%2F11c206rp2h!19sChIJE6DWTMV5ToYR3746Rw_AnWc?authuser=0&hl=en&rclk=1", "categories": ["Heating", "contractor"], "source_category": "HVAC contractor"}, {"business_name": "Aire Serv of Dallas", "city": "Dallas", "state": "TX", "address": null, "phone": "(214) 838-7191", "website": null, "google_place_id": "0x864c20efad18e845:0", "google_rating": null, "google_review_count": null, "maps_url": "https://www.google.com/maps/place/Aire+Serv+of+Dallas/data=!4m7!3m6!1s0x864c20efad18e845:0x81de226f9a99566!8m2!3d32.9248142!4d-96.8049997!16s%2Fg%2F1td_y_kh!19sChIJRegYre8gTIYRZpWp-SbiHQg?authuser=0&hl=en&rclk=1", "categories": ["HVAC", "contractor"], "source_category": "HVAC contractor"}, {"business_name": "Jade Air", "city": "Dallas", "state": "TX", "address": "2243 Vagas St", "phone": "(214) 923-7904", "website": null, "google_place_id": "0x864e9eb260468d63:0", "google_rating": null, "google_review_count": null, "maps_url": "https://www.google.com/maps/place/Jade+Air/data=!4m7!3m6!1s0x864e9eb260468d63:0x4f5c708ce6a7239e!8m2!3d32.8060326!4d-96.8231834!16s%2Fg%2F1tnct9j6!19sChIJY41GYLKeToYRniOn5oxwXE8?authuser=0&hl=en&rclk=1", "categories": ["HVAC", "contractor"], "source_category": "HVAC contractor"}, {"business_name": "United States Home Services", "city": "Dallas", "state": "TX", "address": "1805 Royal Ln #101", "phone": "(214) 301-5784", "website": null, "google_place_id": "0x8640c3bf0a955555:0", "google_rating": null, "google_review_count": null, "maps_url": "https://www.google.com/maps/place/United+States+Home+Services/data=!4m7!3m6!1s0x8640c3bf0a955555:0xc5e4e8984ea52d3c!8m2!3d32.8961105!4d-96.9158967!16s%2Fg%2F11qpm35zc2!19sChIJVVWVCr_DQIYRPC2lTpjo5MU?authuser=0&hl=en&rclk=1", "categories": ["HVAC", "contractor"], "source_category": "HVAC contractor"}, {"business_name": "Texas Air Doctors", "city": "Dallas", "state": "TX", "address": "5213 Davis Blvd Suite K", "phone": "(817) 438-8576", "website": null, "google_place_id": "0x864e78f176b8a4bb:0", "google_rating": null, "google_review_count": null, "maps_url": "https://www.google.com/maps/place/Texas+Air+Doctors/data=!4m7!3m6!1s0x864e78f176b8a4bb:0x6f39c3452d062a27!8m2!3d32.8427487!4d-97.2158782!16s%2Fg%2F1hc51y_hj!19sChIJu6S4dvF4ToYRJyoGLUXDOW8?authuser=0&hl=en&rclk=1", "categories": ["HVAC", "contractor"], "source_category": "HVAC contractor"}, {"business_name": "Cozy - D Heating & A/C LLC", "city": "Dallas", "state": "TX", "address": "117 Elston Dr", "phone": "(972) 291-8002", "website": null, "google_place_id": "0x864e8e0eba296d35:0", "google_rating": null, "google_review_count": null, "maps_url": "https://www.google.com/maps/place/Cozy+-+D+Heating+%26+A%2FC+LLC/data=!4m7!3m6!1s0x864e8e0eba296d35:0x8e571cf0bae48614!8m2!3d32.6705078!4d-96.8235617!16s%2Fg%2F1wd3wg6x!19sChIJNW0pug6OToYRFIbkuvAcV44?authuser=0&hl=en&rclk=1", "categories": ["Heating", "contractor"], "source_category": "HVAC contractor"}, {"business_name": "A/C Rescue, Inc.", "city": "Dallas", "state": "TX", "address": "11110 Petal St Ste 100", "phone": null, "website": null, "google_place_id": "0x864ea0b7354557a3:0", "google_rating": null, "google_review_count": null, "maps_url": "https://www.google.com/maps/place/A%2FC+Rescue,+Inc./data=!4m7!3m6!1s0x864ea0b7354557a3:0xbf3751b828fe7ac1!8m2!3d32.8818354!4d-96.6900862!16s%2Fg%2F11f55f002v!19sChIJo1dFNbegToYRwXr-KLhRN78?authuser=0&hl=en&rclk=1", "categories": ["HVAC", "contractor"], "source_category": "HVAC contractor"}, {"business_name": "Service Experts Dallas", "city": "Dallas", "state": "TX", "address": null, "phone": "(972) 619-7607", "website": null, "google_place_id": "0x864c2784832d5ffd:0", "google_rating": null, "google_review_count": null, "maps_url": "https://www.google.com/maps/place/Service+Experts+Dallas/data=!4m7!3m6!1s0x864c2784832d5ffd:0x85e30c4b3d21290d!8m2!3d32.9560673!4d-96.7075108!16s%2Fg%2F1tg81w6v!19sChIJ_V8tg4QnTIYRDSkhPUsM44U?authuser=0&hl=en&rclk=1", "categories": ["HVAC", "contractor"], "source_category": "HVAC contractor"}, {"business_name": "Sala Air Conditioning", "city": "Dallas", "state": "TX", "address": "4530 Mint Way", "phone": "(214) 742-7252", "website": null, "google_place_id": "0x864e9bd9688d4c6f:0", "google_rating": 4.9, "google_review_count": 139, "maps_url": "https://www.google.com/maps/place/Sala+Air+Conditioning/data=!4m7!3m6!1s0x864e9bd9688d4c6f:0xaf27fe7b88885b48!8m2!3d32.6853134!4d-96.8946788!16s%2Fg%2F1tcts22s!19sChIJb0yNaNmbToYRSFuIiHv-J68?authuser=0&hl=en&rclk=1", "categories": ["Air Conditioning", "contractor"], "source_category": "HVAC contractor"}, {"business_name": "Brown Service Company", "city": "Dallas", "state": "TX", "address": "6340 Baker Blvd", "phone": "(817) 284-9204", "website": null, "google_place_id": "0x864e79c77c541759:0", "google_rating": 4.9, "google_review_count": 397, "maps_url": "https://www.google.com/maps/place/Brown+Service+Company/data=!4m7!3m6!1s0x864e79c77c541759:0x4ac3753f2cfcda9b!8m2!3d32.8085655!4d-97.2437526!16s%2Fg%2F1tdy095d!19sChIJWRdUfMd5ToYRm9r8LD91w0o?authuser=0&hl=en&rclk=1", "categories": ["HVAC", "contractor"], "source_category": "HVAC contractor"}, {"business_name": "Appliance & Air Care Experts", "city": "Dallas", "state": "TX", "address": "2701 Fondren Dr #133", "phone": "(972) 771-5987", "website": null, "google_place_id": "0x864e9f0c84c88cbd:0", "google_rating": 4.9, "google_review_count": 516, "maps_url": "https://www.google.com/maps/place/Appliance+%26+Air+Care+Experts/data=!4m7!3m6!1s0x864e9f0c84c88cbd:0x771bdb460ae8e90e!8m2!3d32.8442023!4d-96.7729232!16s%2Fg%2F1tdmf8y7!19sChIJvYzIhAyfToYRDunoCkbbG3c?authuser=0&hl=en&rclk=1", "categories": ["HVAC", "contractor"], "source_category": "HVAC contractor"}, {"business_name": "Hooper Plumbing & Air Conditioning", "city": "Dallas", "state": "TX", "address": "6725 Hillcrest Ave suite a", "phone": "(214) 761-6820", "website": null, "google_place_id": "0x864e9f00cb7fff49:0", "google_rating": 4.8, "google_review_count": 419, "maps_url": "https://www.google.com/maps/place/Hooper+Plumbing+%26+Air+Conditioning/data=!4m7!3m6!1s0x864e9f00cb7fff49:0xf9eac087ae3a42d5!8m2!3d32.848247!4d-96.787157!16s%2Fg%2F1td76_6w!19sChIJSf9_ywCfToYR1UI6rofA6vk?authuser=0&hl=en&rclk=1", "categories": ["Plumbing", "Air Conditioning", "contractor"], "source_category": "HVAC contractor"}, {"business_name": "billyGO Air Conditioning & Plumbing", "city": "Dallas", "state": "TX", "address": "17430 Campbell Rd Suite 207", "phone": "(214) 267-9944", "website": null, "google_place_id": "0x864c27e2d684b025:0", "google_rating": 4.7, "google_review_count": 1268, "maps_url": "https://www.google.com/maps/place/billyGO+Air+Conditioning+%26+Plumbing/data=!4m7!3m6!1s0x864c27e2d684b025:0x34fa5b3031536ba7!8m2!3d32.990359!4d-96.8066838!16s%2Fg%2F11b808sxdl!19sChIJJbCE1uInTIYRp2tTMTBb-jQ?authuser=0&hl=en&rclk=1", "categories": ["Plumbing", "Air Conditioning", "contractor"], "source_category": "HVAC contractor"}, {"business_name": "Moss Heating & Cooling", "city": "Dallas", "state": "TX", "address": "11145 Morrison Ln", "phone": "(972) 733-6802", "website": null, "google_place_id": "0x864e83c9c8a16561:0", "google_rating": 4.9, "google_review_count": 855, "maps_url": "https://www.google.com/maps/place/Moss+Heating+%26+Cooling/data=!4m7!3m6!1s0x864e83c9c8a16561:0xc60a2563eeb8af40!8m2!3d32.8853833!4d-96.8931835!16s%2Fg%2F11rfdctb19!19sChIJYWWhyMmDToYRQK-47mMlCsY?authuser=0&hl=en&rclk=1", "categories": ["Heating", "contractor"], "source_category": "HVAC contractor"}, {"business_name": "Tiger Air", "city": "Dallas", "state": "TX", "address": "17606 Preston Rd", "phone": "(214) 214-6922", "website": null, "google_place_id": "0x864c231548bb8789:0", "google_rating": 5.0, "google_review_count": 433, "maps_url": "https://www.google.com/maps/place/Tiger+Air/data=!4m7!3m6!1s0x864c231548bb8789:0x56d3f8ee61da5df5!8m2!3d32.9918926!4d-96.8003332!16s%2Fg%2F11fh7f6nb4!19sChIJiYe7SBUjTIYR9V3aYe7401Y?authuser=0&hl=en&rclk=1", "categories": ["HVAC", "contractor"], "source_category": "HVAC contractor"}, {"business_name": "Silver Spur Air, Heating, & Plumbing of DFW", "city": "Dallas", "state": "TX", "address": "4204 Garland Dr", "phone": "(682) 324-3936", "website": null, "google_place_id": "0x864e77067f42baef:0", "google_rating": 4.9, "google_review_count": 2198, "maps_url": "https://www.google.com/maps/place/Silver+Spur+Air,+Heating,+%26+Plumbing+of+DFW/data=!4m7!3m6!1s0x864e77067f42baef:0xda9f068c491dce4!8m2!3d32.8300839!4d-97.2832745!16s%2Fg%2F11n_8m4fgz!19sChIJ77pCfwZ3ToYR5NyRxGjwqQ0?authuser=0&hl=en&rclk=1", "categories": ["Plumbing", "Heating", "contractor"], "source_category": "HVAC contractor"}, {"business_name": "Mondragon Mechanical LLC", "city": "Dallas", "state": "TX", "address": "2807 Virgo Ln", "phone": "(972) 214-7002", "website": null, "google_place_id": "0x864c276e96e77db3:0", "google_rating": 4.9, "google_review_count": 515, "maps_url": "https://www.google.com/maps/place/Mondragon+Mechanical+LLC/data=!4m7!3m6!1s0x864c276e96e77db3:0x81de04c76a6d9dc7!8m2!3d32.89106!4d-96.8860983!16s%2Fg%2F11r4svft4k!19sChIJs33nlm4nTIYRx51tascE3oE?authuser=0&hl=en&rclk=1", "categories": ["HVAC", "contractor"], "source_category": "HVAC contractor"}, {"business_name": "Rescue Air and Plumbing", "city": "Dallas", "state": "TX", "address": "9639 Greenville Ave", "phone": "(972) 201-3253", "website": null, "google_place_id": "0x864c1f77b16271e1:0", "google_rating": 4.9, "google_review_count": 3613, "maps_url": "https://www.google.com/maps/place/Rescue+Air+and+Plumbing/data=!4m7!3m6!1s0x864c1f77b16271e1:0x8930b56671f51851!8m2!3d32.9074594!4d-96.7484545!16s%2Fg%2F1ptw52wdg!19sChIJ4XFisXcfTIYRURj1cWa1MIk?authuser=0&hl=en&rclk=1", "categories": ["Plumbing", "HVAC", "contractor"], "source_category": "HVAC contractor"}, {"business_name": "Efficient Home Solutions of Dallas", "city": "Dallas", "state": "TX", "address": null, "phone": "(214) 612-7493", "website": null, "google_place_id": "0x864e9fe86fa54279:0", "google_rating": 4.8, "google_review_count": 103, "maps_url": "https://www.google.com/maps/place/Efficient+Home+Solutions+of+Dallas/data=!4m7!3m6!1s0x864e9fe86fa54279:0xb3089d0e27912a3a!8m2!3d32.8837922!4d-96.769026!16s%2Fg%2F11bbrl706_!19sChIJeUKlb-ifToYROiqRJw6dCLM?authuser=0&hl=en&rclk=1", "categories": ["HVAC", "contractor"], "source_category": "HVAC contractor"}, {"business_name": "Saul Ramirez Heating & A/C", "city": "Dallas", "state": "TX", "address": "1457 Cibola Dr", "phone": "(469) 450-0614", "website": null, "google_place_id": "0x864e9bcc4111cbed:0", "google_rating": 5.0, "google_review_count": 32, "maps_url": "https://www.google.com/maps/place/Saul+Ramirez+Heating+%26+A%2FC/data=!4m7!3m6!1s0x864e9bcc4111cbed:0xe4bd6712e0b452dc!8m2!3d32.7312967!4d-96.9153685!16s%2Fg%2F11j64s7z30!19sChIJ7csRQcybToYR3FK04BJnveQ?authuser=0&hl=en&rclk=1", "categories": ["Heating", "contractor"], "source_category": "HVAC contractor"}, {"business_name": "A Team Heat & Air", "city": "Dallas", "state": "TX", "address": "2232 Moneda St", "phone": "(817) 576-2657", "website": null, "google_place_id": "0x864e797212dc6557:0", "google_rating": 5.0, "google_review_count": 69, "maps_url": "https://www.google.com/maps/place/A+Team+Heat+%26+Air/data=!4m7!3m6!1s0x864e797212dc6557:0x111c6133c2e7e2f2!8m2!3d32.792163!4d-97.2540392!16s%2Fg%2F11p0hdrfzr!19sChIJV2XcEnJ5ToYR8uLnwjNhHBE?authuser=0&hl=en&rclk=1", "categories": ["HVAC", "contractor"], "source_category": "HVAC contractor"}, {"business_name": "Eastin Heating and Air", "city": "Dallas", "state": "TX", "address": "3838 Oak Lawn Ave Suite#1000", "phone": "(972) 278-0613", "website": null, "google_place_id": "0x864e9993c2be252d:0", "google_rating": 4.8, "google_review_count": 477, "maps_url": "https://www.google.com/maps/place/Eastin+Heating+and+Air/data=!4m7!3m6!1s0x864e9993c2be252d:0x6bc5f84142178c96!8m2!3d32.8144645!4d-96.8014862!16s%2Fg%2F1tmz7bmt!19sChIJLSW-wpOZToYRlowXQkH4xWs?authuser=0&hl=en&rclk=1", "categories": ["Heating", "contractor"], "source_category": "HVAC contractor"}, {"business_name": "Sunny Service", "city": "Dallas", "state": "TX", "address": "1500 Central Park Dr", "phone": "(817) 476-3051", "website": null, "google_place_id": "0x864e7913a542b163:0", "google_rating": 4.9, "google_review_count": 2299, "maps_url": "https://www.google.com/maps/place/Sunny+Service/data=!4m7!3m6!1s0x864e7913a542b163:0xc5034bf9e201bae1!8m2!3d32.8074316!4d-97.2079287!16s%2Fg%2F11g7_hpl04!19sChIJY7FCpRN5ToYR4boB4vlLA8U?authuser=0&hl=en&rclk=1", "categories": ["HVAC", "contractor"], "source_category": "HVAC contractor"}, {"business_name": "Air North", "city": "Dallas", "state": "TX", "address": "2530 Glenda Ln STE 100", "phone": "(214) 544-7540", "website": null, "google_place_id": "0x864c192253d6661b:0", "google_rating": 4.8, "google_review_count": 83, "maps_url": "https://www.google.com/maps/place/Air+North/data=!4m7!3m6!1s0x864c192253d6661b:0xa8412bc1d41123a9!8m2!3d32.889194!4d-96.892827!16s%2Fg%2F1wrgkkc9!19sChIJG2bWUyIZTIYRqSMR1MErQag?authuser=0&hl=en&rclk=1", "categories": ["HVAC", "contractor"], "source_category": "HVAC contractor"}, {"business_name": "Air Force One Plumbing Heating & Air, now part of A-Star Air Conditioning & Plumbng", "city": "Dallas", "state": "TX", "address": null, "phone": "(469) 476-4846", "website": null, "google_place_id": "0x864ea1f4bd2408cf:0", "google_rating": 4.6, "google_review_count": 233, "maps_url": "https://www.google.com/maps/place/Air+Force+One+Plumbing+Heating+%26+Air,+now+part+of+A-Star+Air+Conditioning+%26+Plumbng/data=!4m7!3m6!1s0x864ea1f4bd2408cf:0xaea7dbbf2e7c5421!8m2!3d32.9596524!4d-96.672329!16s%2Fg%2F1tlndvyh!19sChIJzwgkvfShToYRIVR8Lr_bp64?authuser=0&hl=en&rclk=1", "categories": ["Plumbing", "Heating", "contractor"], "source_category": "HVAC contractor"}, {"business_name": "Dial One Johnson Plumbing, Cooling & Heating", "city": "Dallas", "state": "TX", "address": "830 S Hampton Rd", "phone": "(469) 517-1240", "website": null, "google_place_id": "0x864e9a3f7d3e6d37:0", "google_rating": 4.9, "google_review_count": 632, "maps_url": "https://www.google.com/maps/place/Dial+One+Johnson+Plumbing,+Cooling+%26+Heating/data=!4m7!3m6!1s0x864e9a3f7d3e6d37:0xa41e7d0be0a0acf3!8m2!3d32.737305!4d-96.8563772!16s%2Fg%2F1261sj890!19sChIJN20-fT-aToYR86yg4At9HqQ?authuser=0&hl=en&rclk=1", "categories": ["Plumbing", "Heating", "contractor"], "source_category": "HVAC contractor"}, {"business_name": "Airtron Heating & Air Conditioning", "city": "Dallas", "state": "TX", "address": "10440 Olympic Dr", "phone": "(214) 556-6792", "website": null, "google_place_id": "0x864e9d0ce2de0f51:0", "google_rating": 4.9, "google_review_count": 5345, "maps_url": "https://www.google.com/maps/place/Airtron+Heating+%26+Air+Conditioning/data=!4m7!3m6!1s0x864e9d0ce2de0f51:0xbb0e13ed3e01371a!8m2!3d32.8649743!4d-96.8858765!16s%2Fg%2F1tk1zg5j!19sChIJUQ_e4gydToYRGjcBPu0TDrs?authuser=0&hl=en&rclk=1", "categories": ["Heating", "contractor"], "source_category": "HVAC contractor"}, {"business_name": "CACTUS COOLING & HEATING", "city": "Dallas", "state": "TX", "address": "2530 W 10th St", "phone": "(214) 817-0448", "website": null, "google_place_id": "0x6d4a8cdd2e3928c9:0", "google_rating": 4.9, "google_review_count": 59, "maps_url": "https://www.google.com/maps/place/CACTUS+COOLING+%26+HEATING/data=!4m7!3m6!1s0x6d4a8cdd2e3928c9:0xced5dca1d0e805fc!8m2!3d32.7448632!4d-96.8601661!16s%2Fg%2F11rhw643xt!19sChIJySg5Lt2MSm0R_AXo0KHc1c4?authuser=0&hl=en&rclk=1", "categories": ["HEATING", "contractor"], "source_category": "HVAC contractor"}]}}