{"source": "contractor_discovery", "identifier": "electrician:garland:tx", "cached_at": "2025-12-11T20:30:41.135941", "data": {"category": "electrician", "city": "Garland", "state": "TX", "total_found": 60, "contractors": [{"business_name": "HR Phoenix Electrical & Plumbing", "city": "Garland", "state": "TX", "address": "7171 Latham Dr", "phone": "(817) 369-5423", "website": null, "google_place_id": "0x864dd97685861a3b:0", "google_rating": null, "google_review_count": null, "maps_url": "https://www.google.com/maps/place/HR+Phoenix+Electrical+%26+Plumbing/data=!4m7!3m6!1s0x864dd97685861a3b:0xe73339c108b76107!8m2!3d32.8073725!4d-97.224854!16s%2Fg%2F11fmpy8zm6!19sChIJOxqGhXbZTYYRB2G3CME5M-c?authuser=0&hl=en&rclk=1", "categories": ["Plumbing", "Electrical"], "source_category": "electrician"}, {"business_name": "TopTech Electric & Plumbing", "city": "Garland", "state": "TX", "address": "7415 Whitehall St #119", "phone": "(682) 327-0649", "website": null, "google_place_id": "0x864e79b2df1fe66f:0", "google_rating": null, "google_review_count": null, "maps_url": "https://www.google.com/maps/place/TopTech+Electric+%26+Plumbing/data=!4m7!3m6!1s0x864e79b2df1fe66f:0xb864c1ae8efbeda3!8m2!3d32.8074953!4d-97.2190254!16s%2Fg%2F11f7by12c2!19sChIJb-Yf37J5ToYRo-37jq7BZLg?authuser=0&hl=en&rclk=1", "categories": ["Plumbing", "Electrician"], "source_category": "electrician"}, {"business_name": "Dennis Stiles Master Electrician & Company, LLC", "city": "Garland", "state": "TX", "address": null, "phone": "(817) 773-2278", "website": null, "google_place_id": "0x864e79250ad1b97f:0", "google_rating": null, "google_review_count": null, "maps_url": "https://www.google.com/maps/place/Dennis+Stiles+Master+Electrician+%26+Company,+LLC/data=!4m7!3m6!1s0x864e79250ad1b97f:0xc35720ec0afcc155!8m2!3d32.7998764!4d-97.031894!16s%2Fg%2F11n8t27g7v!19sChIJf7nRCiV5ToYRVcH8CuwgV8M?authuser=0&hl=en&rclk=1", "categories": ["Electrician"], "source_category": "electrician"}, {"business_name": "Harter Electric LLC.", "city": "Garland", "state": "TX", "address": "2345 Pecan Ct", "phone": "(817) 834-2001", "website": null, "google_place_id": "0x864e79e22e76c5f3:0", "google_rating": null, "google_review_count": null, "maps_url": "https://www.google.com/maps/place/Harter+Electric+LLC./data=!4m7!3m6!1s0x864e79e22e76c5f3:0xcbef81291aa442f7!8m2!3d32.7935319!4d-97.2493156!16s%2Fg%2F1tfgdn5x!19sChIJ88V2LuJ5ToYR90KkGimB78s?authuser=0&hl=en&rclk=1", "categories": ["Electrician"], "source_category": "electrician"}, {"business_name": "Arrow Electric Service", "city": "Garland", "state": "TX", "address": "201 W Hurst Blvd", "phone": "(817) 538-8959", "website": null, "google_place_id": "0x864e7ef32ff531df:0", "google_rating": null, "google_review_count": null, "maps_url": "https://www.google.com/maps/place/Arrow+Electric+Service/data=!4m7!3m6!1s0x864e7ef32ff531df:0x91681ec7fb643f9d!8m2!3d32.8085899!4d-97.1713868!16s%2Fg%2F1tk6w9sx!19sChIJ3zH1L_N-ToYRnT9k-8ceaJE?authuser=0&hl=en&rclk=1", "categories": ["Electrician"], "source_category": "electrician"}, {"business_name": "Hop2It Electrical Repair", "city": "Garland", "state": "TX", "address": "7510 Davis Blvd ste a", "phone": "(817) 373-5093", "website": null, "google_place_id": "0x864e7f14fcfec041:0", "google_rating": null, "google_review_count": null, "maps_url": "https://www.google.com/maps/place/Hop2It+Electrical+Repair/data=!4m7!3m6!1s0x864e7f14fcfec041:0xfaa05793f45cf3df!8m2!3d32.884732!4d-97.2030712!16s%2Fg%2F11c3ywfvyk!19sChIJQcD-_BR_ToYR3_Nc9JNXoPo?authuser=0&hl=en&rclk=1", "categories": ["Electrical"], "source_category": "electrician"}, {"business_name": "F.A.S.T. Services Electric LLC", "city": "Garland", "state": "TX", "address": "3123 Handley Ederville Rd # B", "phone": "(817) 773-7263", "website": null, "google_place_id": "0x864e79f3887b9a49:0", "google_rating": null, "google_review_count": null, "maps_url": "https://www.google.com/maps/place/F.A.S.T.+Services+Electric+LLC/data=!4m7!3m6!1s0x864e79f3887b9a49:0x7d03edefd4ab56bd!8m2!3d32.807869!4d-97.2213691!16s%2Fg%2F11y3zx5_0m!19sChIJSZp7iPN5ToYRvVar1O_tA30?authuser=0&hl=en&rclk=1", "categories": ["Electrician"], "source_category": "electrician"}, {"business_name": "Arrow Electric", "city": "Garland", "state": "TX", "address": "2903 National Dr", "phone": "(972) 926-7007", "website": null, "google_place_id": "0x864ea0b7098f3789:0", "google_rating": null, "google_review_count": null, "maps_url": "https://www.google.com/maps/place/Arrow+Electric/data=!4m7!3m6!1s0x864ea0b7098f3789:0x2526380fa02acde7!8m2!3d32.881504!4d-96.6728961!16s%2Fg%2F1td0gx_p!19sChIJiTePCbegToYR580qoA84JiU?authuser=0&hl=en&rclk=1", "categories": ["Electrician"], "source_category": "electrician"}, {"business_name": "Douglas Electrical Services", "city": "Garland", "state": "TX", "address": "731 N Commerce St", "phone": "(817) 657-1341", "website": null, "google_place_id": "0x864e12a8e2a567af:0", "google_rating": null, "google_review_count": null, "maps_url": "https://www.google.com/maps/place/Douglas+Electrical+Services/data=!4m7!3m6!1s0x864e12a8e2a567af:0x9d3f5aa59cc3928d!8m2!3d32.7682596!4d-97.3396454!16s%2Fg%2F11bwqbwr86!19sChIJr2el4qgSToYRjZLDnKVaP50?authuser=0&hl=en&rclk=1", "categories": ["Electrical"], "source_category": "electrician"}, {"business_name": "Breeze Air, Heat & Electrical", "city": "Garland", "state": "TX", "address": "2402 Gravel Dr", "phone": null, "website": null, "google_place_id": "0x864e7922a595a39d:0", "google_rating": null, "google_review_count": null, "maps_url": "https://www.google.com/maps/place/Breeze+Air,+Heat+%26+Electrical/data=!4m7!3m6!1s0x864e7922a595a39d:0xec4ae19d4cefc24!8m2!3d32.7932311!4d-97.2166037!16s%2Fg%2F11dxslrm3l!19sChIJnaOVpSJ5ToYRJPzO1BmuxA4?authuser=0&hl=en&rclk=1", "categories": ["Electrical"], "source_category": "electrician"}, {"business_name": "S&R Electrical Contractor LLC", "city": "Garland", "state": "TX", "address": "1816 Hickory Dr", "phone": "(214) 907-6761", "website": null, "google_place_id": "0x292978953e69d0b3:0", "google_rating": null, "google_review_count": null, "maps_url": "https://www.google.com/maps/place/S%26R+Electrical+Contractor+LLC/data=!4m7!3m6!1s0x292978953e69d0b3:0xf17ba309c49d95d2!8m2!3d32.784723!4d-97.264814!16s%2Fg%2F11rbyvn87t!19sChIJs9BpPpV4KSkR0pWdxAmje_E?authuser=0&hl=en&rclk=1", "categories": ["Electrical", "Contractor"], "source_category": "electrician"}, {"business_name": "Dependable Electric, LLC", "city": "Garland", "state": "TX", "address": null, "phone": "(817) 715-2225", "website": null, "google_place_id": "0x864e79ee36ff82b5:0", "google_rating": null, "google_review_count": null, "maps_url": "https://www.google.com/maps/place/Dependable+Electric,+LLC/data=!4m7!3m6!1s0x864e79ee36ff82b5:0x9d3fd8dc2c7e5773!8m2!3d32.8380085!4d-97.031894!16s%2Fg%2F11dx9wxzpf!19sChIJtYL_Nu55ToYRc1d-LNzYP50?authuser=0&hl=en&rclk=1", "categories": ["Electrician"], "source_category": "electrician"}, {"business_name": "Milestone Electric, A/C, & Plumbing", "city": "Garland", "state": "TX", "address": "2360 Crist Rd Suite B900", "phone": "(972) 616-4171", "website": null, "google_place_id": "0x864c1d3916af037f:0", "google_rating": null, "google_review_count": null, "maps_url": "https://www.google.com/maps/place/Milestone+Electric,+A%2FC,+%26+Plumbing/data=!4m7!3m6!1s0x864c1d3916af037f:0xe74db6d3a7a1841f!8m2!3d32.9352121!4d-96.6253182!16s%2Fg%2F11sz5pb7pz!19sChIJfwOvFjkdTIYRH4Shp9O2Tec?authuser=0&hl=en&rclk=1", "categories": ["Plumbing", "Electrician"], "source_category": "electrician"}, {"business_name": "Electric Masters", "city": "Garland", "state": "TX", "address": "2605 Western Dr", "phone": "(972) 806-1771", "website": null, "google_place_id": "0x488334c2b1b47cbb:0", "google_rating": null, "google_review_count": null, "maps_url": "https://www.google.com/maps/place/Electric+Masters/data=!4m7!3m6!1s0x488334c2b1b47cbb:0x9ad2330d76174a4f!8m2!3d32.923589!4d-96.6676879!16s%2Fg%2F11xd8mbry6!19sChIJu3y0scI0g0gRT0oXdg0z0po?authuser=0&hl=en&rclk=1", "categories": ["Electrician"], "source_category": "electrician"}, {"business_name": "Straight Up Electrical Tx LLC", "city": "Garland", "state": "TX", "address": "1845 Precinct Line Rd #216", "phone": "(817) 383-0602", "website": null, "google_place_id": "0x864e791ce628e62f:0", "google_rating": null, "google_review_count": null, "maps_url": "https://www.google.com/maps/place/Straight+Up+Electrical+Tx+LLC/data=!4m7!3m6!1s0x864e791ce628e62f:0xd3e723a72e9f4c42!8m2!3d32.8498425!4d-97.1868188!16s%2Fg%2F11lp86jj7w!19sChIJL-Yo5hx5ToYRQkyfLqcj59M?authuser=0&hl=en&rclk=1", "categories": ["Electrical"], "source_category": "electrician"}, {"business_name": "Cooper Electric Service", "city": "Garland", "state": "TX", "address": "5647 Cancun Dr", "phone": "(214) 718-9383", "website": null, "google_place_id": "0x864e7868f8734377:0", "google_rating": null, "google_review_count": null, "maps_url": "https://www.google.com/maps/place/Cooper+Electric+Service/data=!4m7!3m6!1s0x864e7868f8734377:0x258a62e970905af7!8m2!3d32.8501749!4d-97.2350281!16s%2Fg%2F1tcw8lbl!19sChIJd0Nz-Gh4ToYR91qQcOliiiU?authuser=0&hl=en&rclk=1", "categories": ["Electrician"], "source_category": "electrician"}, {"business_name": "Circle-E Facility & Home Services", "city": "Garland", "state": "TX", "address": "2951 Northern Cross Blvd", "phone": "(817) 355-0044", "website": null, "google_place_id": "0x864e7e48f11b6847:0", "google_rating": null, "google_review_count": null, "maps_url": "https://www.google.com/maps/place/Circle-E+Facility+%26+Home+Services/data=!4m7!3m6!1s0x864e7e48f11b6847:0x99894c04feb4e965!8m2!3d32.8372891!4d-97.3068545!16s%2Fg%2F1thqb80g!19sChIJR2gb8Uh-ToYRZem0_gRMiZk?authuser=0&hl=en&rclk=1", "categories": ["Electrician"], "source_category": "electrician"}, {"business_name": "Mr. Electric of Garland", "city": "Garland", "state": "TX", "address": "3256 Southern Dr Ste. 465D", "phone": "(469) 589-7398", "website": null, "google_place_id": "0x864ea7f9bed8118d:0", "google_rating": null, "google_review_count": null, "maps_url": "https://www.google.com/maps/place/Mr.+Electric+of+Garland/data=!4m7!3m6!1s0x864ea7f9bed8118d:0x7edbcbf0c9068207!8m2!3d32.8784953!4d-96.6176806!16s%2Fg%2F11tjl3dc_6!19sChIJjRHYvvmnToYRB4IGyfDL234?authuser=0&hl=en&rclk=1", "categories": ["Electrician"], "source_category": "electrician"}, {"business_name": "Safe Plug Electric Garland", "city": "Garland", "state": "TX", "address": "2013 Glencrest Ln", "phone": "(214) 380-0034", "website": null, "google_place_id": "0x22748fc96724f08d:0", "google_rating": null, "google_review_count": null, "maps_url": "https://www.google.com/maps/place/Safe+Plug+Electric+Garland/data=!4m7!3m6!1s0x22748fc96724f08d:0xf33ae14b94ac87d7!8m2!3d32.9316106!4d-96.6359072!16s%2Fg%2F11sx532btn!19sChIJjfAkZ8mPdCIR14eslEvhOvM?authuser=0&hl=en&rclk=1", "categories": ["Electrician"], "source_category": "electrician"}, {"business_name": "Electrics Contractor Pros", "city": "Garland", "state": "TX", "address": "3304 W Walnut St", "phone": "(903) 568-8907", "website": null, "google_place_id": "0x864c1f64c666c53b:0", "google_rating": 5.0, "google_review_count": 21, "maps_url": "https://www.google.com/maps/place/Electrics+Contractor+Pros/data=!4m7!3m6!1s0x864c1f64c666c53b:0xfea01962106f8731!8m2!3d32.916298!4d-96.67996!16s%2Fg%2F11rxj8r22f!19sChIJO8VmxmQfTIYRMYdvEGIZoP4?authuser=0&hl=en&rclk=1", "categories": ["Electrician", "Contractor"], "source_category": "electrician"}, {"business_name": "Epic Electrical", "city": "Garland", "state": "TX", "address": null, "phone": "(682) 478-6088", "website": null, "google_place_id": "0x864e803d4dd1793b:0", "google_rating": 5.0, "google_review_count": 108, "maps_url": "https://www.google.com/maps/place/Epic+Electrical/data=!4m7!3m6!1s0x864e803d4dd1793b:0xc27e63ba1a480a79!8m2!3d32.8811165!4d-97.1926549!16s%2Fg%2F1s04c0k8z!19sChIJO3nRTT2AToYReQpIGrpjfsI?authuser=0&hl=en&rclk=1", "categories": ["Electrical"], "source_category": "electrician"}, {"business_name": "Mister Sparky Electrician DFW", "city": "Garland", "state": "TX", "address": "4827 W Royal Ln Suite B", "phone": "(214) 613-0481", "website": null, "google_place_id": "0x864ea733ee7ec8af:0", "google_rating": 4.9, "google_review_count": 914, "maps_url": "https://www.google.com/maps/place/Mister+Sparky+Electrician+DFW/data=!4m7!3m6!1s0x864ea733ee7ec8af:0x7e62382f867262aa!8m2!3d32.9221444!4d-97.0149426!16s%2Fg%2F1pycm8szf!19sChIJr8h-7jOnToYRqmJyhi84Yn4?authuser=0&hl=en&rclk=1", "categories": ["Electrician"], "source_category": "electrician"}, {"business_name": "Elizabethtown Electrical", "city": "Garland", "state": "TX", "address": "13291 Raceway Dr", "phone": "(817) 529-8409", "website": null, "google_place_id": "0x864ddb36b48264b5:0", "google_rating": 5.0, "google_review_count": 1, "maps_url": "https://www.google.com/maps/place/Elizabethtown+Electrical/data=!4m7!3m6!1s0x864ddb36b48264b5:0x807d549e01ba0568!8m2!3d33.0251534!4d-97.2707052!16s%2Fg%2F11k57kwrhw!19sChIJtWSCtDbbTYYRaAW6AZ5UfYA?authuser=0&hl=en&rclk=1", "categories": ["Electrical"], "source_category": "electrician"}, {"business_name": "1st Choice Electrics", "city": "Garland", "state": "TX", "address": "1618 Wynn Joyce Rd", "phone": "(346) 398-0623", "website": null, "google_place_id": "0x864ea79b0f49d709:0", "google_rating": 5.0, "google_review_count": 23, "maps_url": "https://www.google.com/maps/place/1st+Choice+Electrics/data=!4m7!3m6!1s0x864ea79b0f49d709:0x655135a65a4c7e05!8m2!3d32.8639183!4d-96.6059756!16s%2Fg%2F11rxj93kld!19sChIJCddJD5unToYRBX5MWqY1UWU?authuser=0&hl=en&rclk=1", "categories": ["Electrician"], "source_category": "electrician"}, {"business_name": "Big State Electricians-Garland", "city": "Garland", "state": "TX", "address": "5716 Marina Dr", "phone": "(469) 240-2810", "website": null, "google_place_id": "0x864ea8f0e0f0131b:0", "google_rating": 5.0, "google_review_count": 4, "maps_url": "https://www.google.com/maps/place/Big+State+Electricians-Garland/data=!4m7!3m6!1s0x864ea8f0e0f0131b:0xaa6355caef802559!8m2!3d32.8555412!4d-96.5487749!16s%2Fg%2F11gbl0fmc9!19sChIJGxPw4PCoToYRWSWA78pVY6o?authuser=0&hl=en&rclk=1", "categories": ["Electrician"], "source_category": "electrician"}, {"business_name": "Russ Electric", "city": "Garland", "state": "TX", "address": "1713 Hill Creek Dr", "phone": "(972) 272-8803", "website": null, "google_place_id": "0x864ea09fb9320d99:0", "google_rating": 4.9, "google_review_count": 291, "maps_url": "https://www.google.com/maps/place/Russ+Electric/data=!4m7!3m6!1s0x864ea09fb9320d99:0xa3739010e8962427!8m2!3d32.8641117!4d-96.5808769!16s%2Fg%2F1hc2m6ggj!19sChIJmQ0yuZ-gToYRJySW6BCQc6M?authuser=0&hl=en&rclk=1", "categories": ["Electrician"], "source_category": "electrician"}, {"business_name": "All-In-One Electric", "city": "Garland", "state": "TX", "address": "500 E Arapaho Rd #201", "phone": "(214) 878-0741", "website": null, "google_place_id": "0x864c1f1078a03559:0", "google_rating": 4.7, "google_review_count": 77, "maps_url": "https://www.google.com/maps/place/All-In-One+Electric/data=!4m7!3m6!1s0x864c1f1078a03559:0xe77efb8be06a8fb3!8m2!3d32.9575585!4d-96.7169903!16s%2Fg%2F1tfgk6gb!19sChIJWTWgeBAfTIYRs49q4Iv7fuc?authuser=0&hl=en&rclk=1", "categories": ["Electrician"], "source_category": "electrician"}, {"business_name": "Birdsong Electric Inc", "city": "Garland", "state": "TX", "address": "2914 Industrial Ln", "phone": "(972) 295-3000", "website": null, "google_place_id": "0x864ea0b82d962d2b:0", "google_rating": 4.4, "google_review_count": 20, "maps_url": "https://www.google.com/maps/place/Birdsong+Electric+Inc/data=!4m7!3m6!1s0x864ea0b82d962d2b:0xfca80519ca2795f0!8m2!3d32.8810572!4d-96.6751071!16s%2Fg%2F1tdbr8jm!19sChIJKy2WLbigToYR8JUnyhkFqPw?authuser=0&hl=en&rclk=1", "categories": ["Electrician"], "source_category": "electrician"}, {"business_name": "Electrician On Call", "city": "Garland", "state": "TX", "address": "6703 Levelland Rd Suite B", "phone": "(214) 235-7251", "website": null, "google_place_id": "0x864c23d4c7e432b3:0", "google_rating": 4.9, "google_review_count": 693, "maps_url": "https://www.google.com/maps/place/Electrician+On+Call/data=!4m7!3m6!1s0x864c23d4c7e432b3:0xe52ab82401b3438a!8m2!3d32.9884168!4d-96.7929887!16s%2Fg%2F1262rgwg6!19sChIJszLkx9QjTIYRikOzASS4KuU?authuser=0&hl=en&rclk=1", "categories": ["Electrician"], "source_category": "electrician"}, {"business_name": "Huggins Electric", "city": "Garland", "state": "TX", "address": "5900 Huddleston St", "phone": "(817) 626-3336", "website": null, "google_place_id": "0x864dd810ae4d1d11:0", "google_rating": 4.4, "google_review_count": 59, "maps_url": "https://www.google.com/maps/place/Huggins+Electric/data=!4m7!3m6!1s0x864dd810ae4d1d11:0x95fa1cd1bc287d36!8m2!3d32.8567414!4d-97.2661272!16s%2Fg%2F1vq9mpm_!19sChIJER1NrhDYTYYRNn0ovNEc-pU?authuser=0&hl=en&rclk=1", "categories": ["Electrician"], "source_category": "electrician"}, {"business_name": "Marquez Electric LLC", "city": "Garland", "state": "TX", "address": null, "phone": "(214) 392-6743", "website": null, "google_place_id": "0x8492439d64949901:0", "google_rating": 5.0, "google_review_count": 11, "maps_url": "https://www.google.com/maps/place/Marquez+Electric+LLC/data=!4m7!3m6!1s0x8492439d64949901:0x7d247b129b57c3bc!8m2!3d32.9625981!4d-96.9486!16s%2Fg%2F11t3jqqyx2!19sChIJAZmUZJ1DkoQRvMNXmxJ7JH0?authuser=0&hl=en&rclk=1", "categories": ["Electrician"], "source_category": "electrician"}, {"business_name": "W3 Electric", "city": "Garland", "state": "TX", "address": "3101 Main St", "phone": "(972) 793-0733", "website": null, "google_place_id": "0x864ea973bb2d80bd:0", "google_rating": 5.0, "google_review_count": 1244, "maps_url": "https://www.google.com/maps/place/W3+Electric/data=!4m7!3m6!1s0x864ea973bb2d80bd:0xea746c3bc1e95aaf!8m2!3d32.9026319!4d-96.5723748!16s%2Fg%2F11fpjs9ft0!19sChIJvYAtu3OpToYRr1rpwTtsdOo?authuser=0&hl=en&rclk=1", "categories": ["Electrician"], "source_category": "electrician"}, {"business_name": "Zamora 7 Electric", "city": "Garland", "state": "TX", "address": null, "phone": "(214) 274-6299", "website": null, "google_place_id": "0x864ea7d9f6bf99db:0", "google_rating": 4.0, "google_review_count": 4, "maps_url": "https://www.google.com/maps/place/Zamora+7+Electric/data=!4m7!3m6!1s0x864ea7d9f6bf99db:0x381ac7e9f866f246!8m2!3d32.7412686!4d-96.736998!16s%2Fg%2F11gyxh816j!19sChIJ25m_9tmnToYRRvJm-OnHGjg?authuser=0&hl=en&rclk=1", "categories": ["Electrician"], "source_category": "electrician"}, {"business_name": "Regions Electric, Inc.", "city": "Garland", "state": "TX", "address": "200 Rayburn St", "phone": "(972) 272-7220", "website": null, "google_place_id": "0x864c1d844d090b0f:0", "google_rating": 4.6, "google_review_count": 11, "maps_url": "https://www.google.com/maps/place/Regions+Electric,+Inc./data=!4m7!3m6!1s0x864c1d844d090b0f:0x73a6ad1323d2bea1!8m2!3d32.9109897!4d-96.6289198!16s%2Fg%2F11c1vj35c8!19sChIJDwsJTYQdTIYRob7SIxOtpnM?authuser=0&hl=en&rclk=1", "categories": ["Electrician"], "source_category": "electrician"}, {"business_name": "Archetype Electric", "city": "Garland", "state": "TX", "address": null, "phone": "(972) 503-9357", "website": null, "google_place_id": "0x6820f640f9d79e03:0", "google_rating": 4.9, "google_review_count": 79, "maps_url": "https://www.google.com/maps/place/Archetype+Electric/data=!4m7!3m6!1s0x6820f640f9d79e03:0xbd5a81c49149f209!8m2!3d32.9596524!4d-96.711846!16s%2Fg%2F11lcgh_3lx!19sChIJA57X-UD2IGgRCfJJkcSBWr0?authuser=0&hl=en&rclk=1", "categories": ["Electrician"], "source_category": "electrician"}, {"business_name": "ElectricMan", "city": "Garland", "state": "TX", "address": null, "phone": "(972) 362-1804", "website": null, "google_place_id": "0x864c1f866e7d1f89:0", "google_rating": 4.8, "google_review_count": 567, "maps_url": "https://www.google.com/maps/place/ElectricMan/data=!4m7!3m6!1s0x864c1f866e7d1f89:0x16f8b59f7b92a385!8m2!3d32.9326396!4d-96.7448392!16s%2Fg%2F1tj2j8_t!19sChIJiR99boYfTIYRhaOSe5-1-BY?authuser=0&hl=en&rclk=1", "categories": ["Electrician"], "source_category": "electrician"}, {"business_name": "Electrical Service Technician", "city": "Garland", "state": "TX", "address": "164 Lake Dr", "phone": "(469) 258-2554", "website": null, "google_place_id": "0x864ea74232dfdfb7:0", "google_rating": null, "google_review_count": null, "maps_url": "https://www.google.com/maps/place/Electrical+Service+Technician/data=!4m7!3m6!1s0x864ea74232dfdfb7:0x500f4bcf60ac16f6!8m2!3d32.8993142!4d-96.627562!16s%2Fg%2F11h1bbgr1x!19sChIJt9_fMkKnToYR9hasYM9LD1A?authuser=0&hl=en&rclk=1", "categories": ["Electrical"], "source_category": "electrician"}, {"business_name": "Mr. Electric of Dallas", "city": "Garland", "state": "TX", "address": "8500 N Stemmons Fwy Suite #3024", "phone": "(469) 634-0316", "website": null, "google_place_id": "0x864e9c5c0ef30433:0", "google_rating": 4.8, "google_review_count": 1155, "maps_url": "https://www.google.com/maps/place/Mr.+Electric+of+Dallas/data=!4m7!3m6!1s0x864e9c5c0ef30433:0xe996be0f558ceb67!8m2!3d32.8022329!4d-96.8323877!16s%2Fg%2F11g77sjlgt!19sChIJMwTzDlycToYRZ-uMVQ--luk?authuser=0&hl=en&rclk=1", "categories": ["Electrician"], "source_category": "electrician"}, {"business_name": "B&B Electric", "city": "Garland", "state": "TX", "address": "1361 W Euless Blvd Suite 111", "phone": "(817) 600-8376", "website": null, "google_place_id": "0x864e8012d1343017:0", "google_rating": 5.0, "google_review_count": 205, "maps_url": "https://www.google.com/maps/place/B%26B+Electric/data=!4m7!3m6!1s0x864e8012d1343017:0x76219cfce34ab0a6!8m2!3d32.8259203!4d-97.1046907!16s%2Fg%2F11cnc57mc_!19sChIJFzA00RKAToYRprBK4_ycIXY?authuser=0&hl=en&rclk=1", "categories": ["Electrician"], "source_category": "electrician"}, {"business_name": "Edison Electricians of Garland", "city": "Garland", "state": "TX", "address": "3313 Naaman School Rd Ste 300", "phone": null, "website": null, "google_place_id": "0x864c1d212ae94c71:0", "google_rating": 5.0, "google_review_count": 3, "maps_url": "https://www.google.com/maps/place/Edison+Electricians+of+Garland/data=!4m7!3m6!1s0x864c1d212ae94c71:0xb931f1f5b61fd948!8m2!3d32.9480681!4d-96.6217104!16s%2Fg%2F11fl7668z6!19sChIJcUzpKiEdTIYRSNkftvXxMbk?authuser=0&hl=en&rclk=1", "categories": ["Electrician"], "source_category": "electrician"}, {"business_name": "Gartech Electrical LLC", "city": "Garland", "state": "TX", "address": null, "phone": "(469) 432-9733", "website": null, "google_place_id": "0x864ebb04c447a613:0", "google_rating": 4.8, "google_review_count": 69, "maps_url": "https://www.google.com/maps/place/Gartech+Electrical+LLC/data=!4m7!3m6!1s0x864ebb04c447a613:0x1d1e9f57104e9bee!8m2!3d32.8259455!4d-96.6363695!16s%2Fg%2F11h6q53w_g!19sChIJE6ZHxAS7ToYR7ptOEFefHh0?authuser=0&hl=en&rclk=1", "categories": ["Electrical"], "source_category": "electrician"}, {"business_name": "Argueta Electric", "city": "Garland", "state": "TX", "address": null, "phone": "(469) 767-3986", "website": null, "google_place_id": "0x864c1d5f4258baa7:0", "google_rating": 5.0, "google_review_count": 5, "maps_url": "https://www.google.com/maps/place/Argueta+Electric/data=!4m7!3m6!1s0x864c1d5f4258baa7:0x13515674ce4170c!8m2!3d31.5932504!4d-97.5813299!16s%2Fg%2F11m40b74hf!19sChIJp7pYQl8dTIYRDBfkTGcVNQE?authuser=0&hl=en&rclk=1", "categories": ["Electrician"], "source_category": "electrician"}, {"business_name": "Puckett", "city": "Garland", "state": "TX", "address": "2602 Industrial Ln #2301", "phone": "(972) 864-0020", "website": null, "google_place_id": "0x864ea0ba6131f361:0", "google_rating": 4.6, "google_review_count": 21, "maps_url": "https://www.google.com/maps/place/Puckett/data=!4m7!3m6!1s0x864ea0ba6131f361:0xf8a8c40ff7b841e3!8m2!3d32.8864087!4d-96.675312!16s%2Fg%2F1tf6xrwc!19sChIJYfMxYbqgToYR40G49w_EqPg?authuser=0&hl=en&rclk=1", "categories": ["Electrician"], "source_category": "electrician"}, {"business_name": "JM Electric Co.", "city": "Garland", "state": "TX", "address": null, "phone": "(469) 504-1212", "website": null, "google_place_id": "0x864c05ce43e08535:0", "google_rating": 5.0, "google_review_count": 43, "maps_url": "https://www.google.com/maps/place/JM+Electric+Co./data=!4m7!3m6!1s0x864c05ce43e08535:0xe015e566cdd154f6!8m2!3d32.946489!4d-96.8285341!16s%2Fg%2F11j7hkctcw!19sChIJNYXgQ84FTIYR9lTRzWblFeA?authuser=0&hl=en&rclk=1", "categories": ["Electrician"], "source_category": "electrician"}, {"business_name": "Echo Electrical Services, Inc.", "city": "Garland", "state": "TX", "address": "3610 W Pioneer Pkwy Ste D", "phone": "(817) 587-6304", "website": null, "google_place_id": "0x864e7cbc3d1cf24d:0", "google_rating": 5.0, "google_review_count": 174, "maps_url": "https://www.google.com/maps/place/Echo+Electrical+Services,+Inc./data=!4m7!3m6!1s0x864e7cbc3d1cf24d:0xdda9b9129668935d!8m2!3d32.7127954!4d-97.1638048!16s%2Fg%2F11b6gnksvk!19sChIJTfIcPbx8ToYRXZNolhK5qd0?authuser=0&hl=en&rclk=1", "categories": ["Electrical"], "source_category": "electrician"}, {"business_name": "Garland Electric", "city": "Garland", "state": "TX", "address": "717 Austin St", "phone": null, "website": null, "google_place_id": "0x864c1d03f7f12c7b:0", "google_rating": 5.0, "google_review_count": 4, "maps_url": "https://www.google.com/maps/place/Garland+Electric/data=!4m7!3m6!1s0x864c1d03f7f12c7b:0xc687159b9a9a304c!8m2!3d32.914062!4d-96.6399368!16s%2Fg%2F11g3zvrc5w!19sChIJeyzx9wMdTIYRTDCampsVh8Y?authuser=0&hl=en&rclk=1", "categories": ["Electrician"], "source_category": "electrician"}, {"business_name": "Richardson Ready Electric Inc.", "city": "Garland", "state": "TX", "address": "620 N Interurban St", "phone": "(972) 234-5092", "website": null, "google_place_id": "0x864c1f13154bb871:0", "google_rating": 4.2, "google_review_count": 38, "maps_url": "https://www.google.com/maps/place/Richardson+Ready+Electric+Inc./data=!4m7!3m6!1s0x864c1f13154bb871:0xd01ff769bc3803a6!8m2!3d32.958336!4d-96.726654!16s%2Fg%2F1thq130z!19sChIJcbhLFRMfTIYRpgM4vGn3H9A?authuser=0&hl=en&rclk=1", "categories": ["Electrician"], "source_category": "electrician"}, {"business_name": "Texla Electric LLC", "city": "Garland", "state": "TX", "address": "6914 Danridge Rd", "phone": "(469) 803-0178", "website": null, "google_place_id": "0x864c03452538211f:0", "google_rating": 4.4, "google_review_count": 18, "maps_url": "https://www.google.com/maps/place/Texla+Electric+LLC/data=!4m7!3m6!1s0x864c03452538211f:0x80408a768e0d4ebb!8m2!3d32.9284027!4d-96.5326413!16s%2Fg%2F11hfl5gyrx!19sChIJHyE4JUUDTIYRu04NjnaKQIA?authuser=0&hl=en&rclk=1", "categories": ["Electrician"], "source_category": "electrician"}, {"business_name": "Tioga Plumbing & Electric", "city": "Garland", "state": "TX", "address": "136 S Norwood Dr", "phone": "(469) 215-2258", "website": null, "google_place_id": "0x864e7ec81f726489:0", "google_rating": 4.8, "google_review_count": 898, "maps_url": "https://www.google.com/maps/place/Tioga+Plumbing+%26+Electric/data=!4m7!3m6!1s0x864e7ec81f726489:0x2c642b2f59ea2f8b!8m2!3d32.8064239!4d-97.1694854!16s%2Fg%2F1q62dlqxl!19sChIJiWRyH8h-ToYRiy_qWS8rZCw?authuser=0&hl=en&rclk=1", "categories": ["Plumbing", "Electrician"], "source_category": "electrician"}, {"business_name": "Motive Power Systems, Inc.", "city": "Garland", "state": "TX", "address": "2410 Minnis Dr", "phone": "(817) 589-7753", "website": null, "google_place_id": "0x864e79ec98d193a3:0", "google_rating": 5.0, "google_review_count": 2, "maps_url": "https://www.google.com/maps/place/Motive+Power+Systems,+Inc./data=!4m7!3m6!1s0x864e79ec98d193a3:0x18ce10ba4a61dd45!8m2!3d32.7963718!4d-97.2438369!16s%2Fg%2F1tcv1vvd!19sChIJo5PRmOx5ToYRRd1hSroQzhg?authuser=0&hl=en&rclk=1", "categories": ["Electrician"], "source_category": "electrician"}, {"business_name": "Cole electric", "city": "Garland", "state": "TX", "address": "2401 Executive Dr", "phone": "(214) 620-4900", "website": null, "google_place_id": "0x864ea17366d24241:0", "google_rating": 5.0, "google_review_count": 1, "maps_url": "https://www.google.com/maps/place/Cole+electric/data=!4m7!3m6!1s0x864ea17366d24241:0xac59249adee04508!8m2!3d32.8880895!4d-96.6819237!16s%2Fg%2F11fmsg8823!19sChIJQULSZnOhToYRCEXg3pokWaw?authuser=0&hl=en&rclk=1", "categories": ["Electrician"], "source_category": "electrician"}, {"business_name": "BH3 Residential and Commercial Electricians", "city": "Garland", "state": "TX", "address": null, "phone": "(972) 761-1973", "website": null, "google_place_id": "0x864ead20bb64ecd7:0", "google_rating": 4.9, "google_review_count": 145, "maps_url": "https://www.google.com/maps/place/BH3+Residential+and+Commercial+Electricians/data=!4m7!3m6!1s0x864ead20bb64ecd7:0xc470db7fe6711263!8m2!3d32.7959068!4d-96.6607668!16s%2Fg%2F11l_c50cqg!19sChIJ1-xkuyCtToYRYxJx5n_bcMQ?authuser=0&hl=en&rclk=1", "categories": ["Electrician"], "source_category": "electrician"}, {"business_name": "AA All Electric Service", "city": "Garland", "state": "TX", "address": null, "phone": "(817) 735-4800", "website": null, "google_place_id": "0x864e73b45dd9ee3f:0", "google_rating": 4.6, "google_review_count": 64, "maps_url": "https://www.google.com/maps/place/AA+All+Electric+Service/data=!4m7!3m6!1s0x864e73b45dd9ee3f:0x47a3668c11bfc17f!8m2!3d32.7409415!4d-97.2447654!16s%2Fg%2F11_v54hwc!19sChIJP-7ZXbRzToYRf8G_EYxmo0c?authuser=0&hl=en&rclk=1", "categories": ["Electrician"], "source_category": "electrician"}, {"business_name": "Mister Sparky Electrician Dallas", "city": "Garland", "state": "TX", "address": "5701 E NW Hwy Ste 1094", "phone": "(214) 972-3110", "website": null, "google_place_id": "0x864e9f6381af337f:0", "google_rating": 4.2, "google_review_count": 24, "maps_url": "https://www.google.com/maps/place/Mister+Sparky+Electrician+Dallas/data=!4m7!3m6!1s0x864e9f6381af337f:0x9a2ad79ee7869618!8m2!3d32.866191!4d-96.7664767!16s%2Fg%2F11b7hk7njr!19sChIJfzOvgWOfToYRGJaG557XKpo?authuser=0&hl=en&rclk=1", "categories": ["Electrician", "HVAC"], "source_category": "electrician"}, {"business_name": "Tesla Electrical Services", "city": "Garland", "state": "TX", "address": null, "phone": "(214) 518-5871", "website": null, "google_place_id": "0x864c02ac675eecaf:0", "google_rating": 5.0, "google_review_count": 8, "maps_url": "https://www.google.com/maps/place/Tesla+Electrical+Services/data=!4m7!3m6!1s0x864c02ac675eecaf:0x7fff491500daac3b!8m2!3d32.8801066!4d-96.557111!16s%2Fg%2F11bzsqfl89!19sChIJr-xeZ6wCTIYRO6zaABVJ_38?authuser=0&hl=en&rclk=1", "categories": ["Electrical"], "source_category": "electrician"}, {"business_name": "Livewire Electric", "city": "Garland", "state": "TX", "address": null, "phone": "(214) 538-2327", "website": null, "google_place_id": "0x864ea7727eb3631b:0", "google_rating": 4.5, "google_review_count": 2, "maps_url": "https://www.google.com/maps/place/Livewire+Electric/data=!4m7!3m6!1s0x864ea7727eb3631b:0xd87711d4ca7468e!8m2!3d32.9125888!4d-96.6388809!16s%2Fg%2F1tdm8r6m!19sChIJG2OzfnKnToYRjkanTB1xhw0?authuser=0&hl=en&rclk=1", "categories": ["Electrician"], "source_category": "electrician"}, {"business_name": "Raines Electric", "city": "Garland", "state": "TX", "address": "521 W Walnut St", "phone": "(972) 272-5595", "website": null, "google_place_id": "0x864c1d9229a2286b:0", "google_rating": 4.0, "google_review_count": 4, "maps_url": "https://www.google.com/maps/place/Raines+Electric/data=!4m7!3m6!1s0x864c1d9229a2286b:0x86ea9dec06165a6!8m2!3d32.9168417!4d-96.6372337!16s%2Fg%2F11hcvzrdwg!19sChIJayiiKZIdTIYRpmVhwN6pbgg?authuser=0&hl=en&rclk=1", "categories": ["Electrician"], "source_category": "electrician"}, {"business_name": "ElectricianPro", "city": "Garland", "state": "TX", "address": null, "phone": "(469) 545-5259", "website": null, "google_place_id": "0x864c1f5bb3a64679:0", "google_rating": 5.0, "google_review_count": 6, "maps_url": "https://www.google.com/maps/place/ElectricianPro/data=!4m7!3m6!1s0x864c1f5bb3a64679:0x89e220519ef13040!8m2!3d32.9641534!4d-96.6910609!16s%2Fg%2F11j8pnx4dd!19sChIJeUams1sfTIYRQDDxnlEg4ok?authuser=0&hl=en&rclk=1", "categories": ["Electrician"], "source_category": "electrician"}, {"business_name": "Fox Electric Co", "city": "Garland", "state": "TX", "address": "1933 Wall St", "phone": "(972) 840-0086", "website": null, "google_place_id": "0x864ea7314585a643:0", "google_rating": 4.4, "google_review_count": 18, "maps_url": "https://www.google.com/maps/place/Fox+Electric+Co/data=!4m7!3m6!1s0x864ea7314585a643:0xeb0d70f0f4818be8!8m2!3d32.8729072!4d-96.6576635!16s%2Fg%2F1w4vkbm0!19sChIJQ6aFRTGnToYR6IuB9PBwDes?authuser=0&hl=en&rclk=1", "categories": ["Electrical"], "source_category": "electrician"}, {"business_name": "Lakewood Electrical", "city": "Garland", "state": "TX", "address": "9214 Angora St", "phone": "(214) 434-8735", "website": null, "google_place_id": "0x864ea17572619bb9:0", "google_rating": 4.6, "google_review_count": 43, "maps_url": "https://www.google.com/maps/place/Lakewood+Electrical/data=!4m7!3m6!1s0x864ea17572619bb9:0x7af1ff0e0e1b90e6!8m2!3d32.8297839!4d-96.7054722!16s%2Fg%2F11b7dv708w!19sChIJuZthcnWhToYR5pAbDg7_8Xo?authuser=0&hl=en&rclk=1", "categories": ["Electrical"], "source_category": "electrician"}]}}